{"Sort_idx": [], "sc_strcts": [["doc", "doc"], ["p", "p"], ["s", "s"], ["g", "g"]], "Lines": [{"Right": [{"class": "", "str": " ist nun zehn Jahre her."}], "hitlen": "", "Tbl_refs": ["soukmagazine.de"], "linegroup": "_", "Kwic": [{"class": "col0 coll", "str": " Blitzeinstieg"}], "ref": "soukmagazine.de", "toknum": 3789239233, "Left": [{"class": "strc", "str": "<p>"}, {"class": "", "str": "Der"}]}, {"Right": [{"class": "", "str": " (Quick-Guide) zur Verf\u00fcgung."}, {"class": "strc", "str": "</p>"}], "hitlen": "", "Tbl_refs": ["ul-segelflug.de"], "linegroup": "_", "Kwic": [{"class": "col0 coll", "str": " Blitzeinstieg"}], "ref": "ul-segelflug.de", "toknum": 1192271076, "Left": [{"class": "", "str": "Und f\u00fcr ganz Eilige steht f\u00fcr einen schnellen \u00dcberblick auch ein"}]}, {"Right": [{"class": "", "str": " in das System, f\u00fcr das dann eigentlich kein Begleitbuch mehr n\u00f6tig ist."}], "hitlen": "", "Tbl_refs": ["morwenna.de"], "linegroup": "_", "Kwic": [{"class": "col0 coll", "str": " Blitzeinstieg"}], "ref": "morwenna.de", "toknum": 15856083693, "Left": [{"class": "", "str": "Eine gute Kenntnis der arthurianischen Welt sichert einen"}]}, {"Right": [{"class": "", "str": " ist jederzeit m\u00f6glich."}, {"class": "strc", "str": "</p>"}], "hitlen": "", "Tbl_refs": ["monsterdoc.de"], "linegroup": "_", "Kwic": [{"class": "col0 coll", "str": " Blitzeinstieg"}], "ref": "monsterdoc.de", "toknum": 6650187566, "Left": [{"class": "", "str": "Ein"}]}, {"Right": [{"class": "", "str": " in die Faszination Clickertraining: wir bringen die grauen Zellen zum Qualmen, entdecken die Talente der Hunde als Denker und Probleml\u00f6ser und wecken Kreativit\u00e4t."}], "hitlen": "", "Tbl_refs": ["doggydogs.de"], "linegroup": "_", "Kwic": [{"class": "col0 coll", "str": "Blitzeinstieg"}], "ref": "doggydogs.de", "toknum": 4540166125, "Left": [{"class": "strc", "str": "<p>"}]}, {"Right": [{"class": "", "str": " ins Klavierspielen wollen oder auf eine etwas \"andere\" Art zu ihrem ehemaligen Hobby zur\u00fcckfinden m\u00f6chten."}, {"class": "strc", "str": "</p>"}], "hitlen": "", "Tbl_refs": ["pianointensiv.de"], "linegroup": "_", "Kwic": [{"class": "col0 coll", "str": " Blitzeinstieg"}], "ref": "pianointensiv.de", "toknum": 8544488049, "Left": [{"class": "strc", "str": "<p>"}, {"class": "", "str": "Der \"Klavier Explorer\" ist die ideale \"Kick-Off-Veranstaltung\" f\u00fcr alle, die einen"}]}, {"Right": [{"class": "", "str": " ins Klavier spielen f\u00fcr Erwachsene: Ich biete zwei Varianten an, n\u00e4mlich den Workshop \"Klavier Explorer\" und die intensiven Einzelcoachings."}], "hitlen": "", "Tbl_refs": ["pianointensiv.de"], "linegroup": "_", "Kwic": [{"class": "col0 coll", "str": " Blitzeinstieg"}], "ref": "pianointensiv.de", "toknum": 18655339096, "Left": [{"class": "strc", "str": "<p>"}, {"class": "", "str": "Schnellkurse (\"Crash-Kurse\") f\u00fcr den"}]}, {"Right": [{"class": "", "str": "\", S.42) weckt ohne \u00fcberfl\u00fcssige Theorie die Begeisterung des Lesers, der innerhalb weniger Minuten einen tollen Effekt auf ein Bild seiner Wahl anwenden kann."}], "hitlen": "", "Tbl_refs": ["terrashop.de"], "linegroup": "_", "Kwic": [{"class": "col0 coll", "str": "Blitzeinstieg"}], "ref": "terrashop.de", "toknum": 7497104398, "Left": [{"class": "strc", "str": "<p>"}, {"class": "", "str": "Bereits der erste Workshop (\""}]}, {"Right": [{"class": "", "str": "; aber als Erg\u00e4nzung empfehle ich dringend eine praxisbezogene Ansicht wie z.B. \ufffdCloud Computing Explained\ufffd oder \ufffdCloud Computing: Implementation, Management, and Security\ufffd."}], "hitlen": "", "Tbl_refs": ["meine-laptoptipps.de"], "linegroup": "_", "Kwic": [{"class": "col0 coll", "str": " Blitzeinstieg"}], "ref": "meine-laptoptipps.de", "toknum": 8529081826, "Left": [{"class": "strc", "str": "<p>"}, {"class": "", "str": "Einfacher \u00dcberblick f\u00fcr den"}]}, {"Right": [{"class": "", "str": " die freie Definition der Kunden-, Produkt- und Bezugss\u00e4ule."}], "hitlen": "", "Tbl_refs": ["3x3managementinstitut.de"], "linegroup": "_", "Kwic": [{"class": "col0 coll", "str": " Blitzeinstieg"}], "ref": "3x3managementinstitut.de", "toknum": 14002604741, "Left": [{"class": "", "str": "Es gen\u00fcgt bereits als"}]}, {"Right": [{"class": "", "str": " in Agricola:"}, {"class": "strc", "str": "</p>"}], "hitlen": "", "Tbl_refs": ["cliquenabend.de"], "linegroup": "_", "Kwic": [{"class": "col0 coll", "str": " Blitzeinstieg"}], "ref": "cliquenabend.de", "toknum": 647187918, "Left": [{"class": "strc", "str": "<p>"}, {"class": "", "str": "21. Dezember -"}]}, {"Right": [{"class": "", "str": " ins Autogene Training"}, {"class": "strc", "str": "</p>"}], "hitlen": "", "Tbl_refs": ["readers-edition.de"], "linegroup": "_", "Kwic": [{"class": "col0 coll", "str": "Blitzeinstieg"}], "ref": "readers-edition.de", "toknum": 7614761433, "Left": [{"class": "strc", "str": "<p>"}]}, {"Right": [{"class": "", "str": " in die Charts"}, {"class": "strc", "str": "</p>"}], "hitlen": "", "Tbl_refs": ["spielemagazin.de"], "linegroup": "_", "Kwic": [{"class": "col0 coll", "str": "Blitzeinstieg"}], "ref": "spielemagazin.de", "toknum": 19359941645, "Left": [{"class": "strc", "str": "<p>"}]}], "request": {"username": "spahic", "gdex_enabled": "1", "pagesize": "200", "format": "json", "lpos": "-n", "q": "q[lemma=\"Blitzeinstieg\"]", "viewmode": "sentence", "async": "0", "corpname": "detenten13_rft3", "api_key": "159b841f61a64092bc630d20b0f56c93"}, "q": ["q[lemma=\"Blitzeinstieg\"]", "e100 "], "righttoleft": false, "finished": 1, "relsize": 0.0, "gdex_scores": {"3789239233": 0.85, "8529081826": 0.5044444444444445, "1192271076": 0.75, "14002604741": 0.22058823529411767, "19359941645": 0.0, "647187918": 0.18749999999999997, "15856083693": 0.7217391304347825, "6650187566": 0.6770833333333333, "4540166125": 0.5968981481481481, "8544488049": 0.5553571428571429, "7497104398": 0.5194444444444444, "18655339096": 0.5307575757575758, "7614761433": 0.0}, "Desc": [{"nicearg": "Blitzeinstieg", "tourl": "q=q%5Blemma%3D%22Blitzeinstieg%22%5D", "rel": 0.0, "arg": "[lemma=\"Blitzeinstieg\"]", "op": "Query", "size": 13}, {"nicearg": "", "tourl": "q=q%5Blemma%3D%22Blitzeinstieg%22%5D&q=e100+", "rel": 0.0, "arg": "100 ", "op": "GDEX", "size": 13}], "concsize": 13, "port": 0, "api_version": "3.112.9", "fullsize": 13}