{"Sort_idx": [], "sc_strcts": [["doc", "doc"], ["p", "p"], ["s", "s"], ["g", "g"]], "Lines": [{"Right": [{"class": "", "str": " von neun Monaten unkritisch wiedergegeben hat."}, {"class": "strc", "str": "</p>"}], "hitlen": "", "Tbl_refs": ["berliner-literaturkritik.de"], "linegroup": "_", "Kwic": [{"class": "col0 coll", "str": " Blitz-Bauzeit"}], "ref": "berliner-literaturkritik.de", "toknum": 5894023535, "Left": [{"class": "strc", "str": "<p>"}, {"class": "", "str": "Wie hartn\u00e4ckig auch sechzig Jahre nach Kriegsende die Mythen rund um den Bau der Reichskanzlei gepflegt werden, mag die Tatsache illustrieren, dass noch im Herbst 2004 das ZDF in Guido Knopps Reihe \"Hitlers Manager\" in der Folge \u00fcber Albert Speer die alte Propagandal\u00fcge von der"}]}], "request": {"username": "spahic", "gdex_enabled": "1", "pagesize": "200", "format": "json", "lpos": "-n", "q": "q[lemma=\"Blitz-Bauzeit\"]", "viewmode": "sentence", "async": "0", "corpname": "detenten13_rft3", "api_key": "159b841f61a64092bc630d20b0f56c93"}, "q": ["q[lemma=\"Blitz-Bauzeit\"]", "e100 "], "righttoleft": false, "finished": 1, "relsize": 0.0, "gdex_scores": {"5894023535": 0.0}, "Desc": [{"nicearg": "Blitz-Bauzeit", "tourl": "q=q%5Blemma%3D%22Blitz-Bauzeit%22%5D", "rel": 0.0, "arg": "[lemma=\"Blitz-Bauzeit\"]", "op": "Query", "size": 1}, {"nicearg": "", "tourl": "q=q%5Blemma%3D%22Blitz-Bauzeit%22%5D&q=e100+", "rel": 0.0, "arg": "100 ", "op": "GDEX", "size": 1}], "concsize": 1, "port": 0, "api_version": "3.112.9", "fullsize": 1}