{"Sort_idx": [], "sc_strcts": [["doc", "doc"], ["p", "p"], ["s", "s"], ["g", "g"]], "Lines": [{"Right": [{"class": "", "str": " wird's wohl nicht gro\u00dfartig anders sein."}], "hitlen": "", "Tbl_refs": ["aggressionshund-forum.de"], "linegroup": "_", "Kwic": [{"class": "col0 coll", "str": " Hundegurus"}], "ref": "aggressionshund-forum.de", "toknum": 13476125511, "Left": [{"class": "", "str": "Bei den"}]}, {"Right": [{"class": "", "str": "\"."}], "hitlen": "", "Tbl_refs": ["aggressionshund-forum.de"], "linegroup": "_", "Kwic": [{"class": "col0 coll", "str": "Hundegurus"}], "ref": "aggressionshund-forum.de", "toknum": 7949441981, "Left": [{"class": "", "str": "Aber die Kassen werden klingeln, das sieht man ja auch bei anderen \""}]}, {"Right": [{"class": "", "str": " steht, tun sie es trotzdem."}], "hitlen": "", "Tbl_refs": ["nomro.de"], "linegroup": "_", "Kwic": [{"class": "col0 coll", "str": " Hundeguru"}], "ref": "nomro.de", "toknum": 19116914759, "Left": [{"class": "", "str": "Aber weil es in irgendeinem Buch von irgendeinem"}]}, {"Right": [{"class": "", "str": " zu lernen."}], "hitlen": "", "Tbl_refs": ["hundemeldungen.de"], "linegroup": "_", "Kwic": [{"class": "col0 coll", "str": " Hundeguru"}], "ref": "hundemeldungen.de", "toknum": 14087305302, "Left": [{"class": "", "str": "Hundefreunde kommen von \u00fcberall her um von"}]}, {"Right": [{"class": "", "str": "\" zuerkannt, denn nur mit mir wurde dieses Abkommen geschlossen."}], "hitlen": "", "Tbl_refs": ["angst-hund.de"], "linegroup": "_", "Kwic": [{"class": "col0 coll", "str": "Hundeguru"}], "ref": "angst-hund.de", "toknum": 5016440025, "Left": [{"class": "", "str": "Gleichzeitig wurde mir auch der Titel \""}]}, {"Right": [{"class": "", "str": " verl\u00e4\u00dft Sie, dann sieht das gleich wieder anders aus."}], "hitlen": "", "Tbl_refs": ["hundeschule-aschaffenburg.de"], "linegroup": "_", "Kwic": [{"class": "col0 coll", "str": " Hundeguru"}], "ref": "hundeschule-aschaffenburg.de", "toknum": 1812112430, "Left": [{"class": "", "str": "Aber wehe, der"}]}, {"Right": [{"class": "", "str": " hat einen Fl\u00e4chenbrand ausgel\u00f6st, den zu l\u00f6schen nun schwierig sein wird."}], "hitlen": "", "Tbl_refs": ["blogspot.de"], "linegroup": "_", "Kwic": [{"class": "col0 coll", "str": " Hundeguru"}], "ref": "blogspot.de", "toknum": 10006909940, "Left": [{"class": "", "str": "Der amerikanische"}]}, {"Right": [{"class": "", "str": "\" geh\u00f6rt, der unvertr\u00e4gliche Hunde wie folgt terapiert hat."}], "hitlen": "", "Tbl_refs": ["yellopet.de"], "linegroup": "_", "Kwic": [{"class": "col0 coll", "str": "Hundeguru"}], "ref": "yellopet.de", "toknum": 19553155305, "Left": [{"class": "", "str": "Vor kurzem habe ich von einem \""}]}, {"Right": [{"class": "", "str": " kennengelernt, der mit 3 Tierheimhunden ohne Leine gehen kann."}], "hitlen": "", "Tbl_refs": ["deine-tierwelt.de"], "linegroup": "_", "Kwic": [{"class": "col0 coll", "str": " Hundeguru"}], "ref": "deine-tierwelt.de", "toknum": 2010817995, "Left": [{"class": "", "str": "Ich habe noch einen"}]}, {"Right": [{"class": "", "str": " begann schon vor Jahrzehnten mit der Ausbildung von Hunden f\u00fcr Dienst & Freizeit."}], "hitlen": "", "Tbl_refs": ["hundemeldungen.de"], "linegroup": "_", "Kwic": [{"class": "col0 coll", "str": "Hundeguru"}], "ref": "hundemeldungen.de", "toknum": 14087305247, "Left": [{"class": "strc", "str": "<p>"}]}, {"Right": [{"class": "", "str": " zeigt Dir in wenigen Schritten, wie das Problem schnell der Vergangenheit angeh\u00f6rt."}, {"class": "strc", "str": "</p>"}], "hitlen": "", "Tbl_refs": ["hunde.de"], "linegroup": "_", "Kwic": [{"class": "col0 coll", "str": "Hundeguru"}], "ref": "hunde.de", "toknum": 7819549509, "Left": []}, {"Right": [{"class": "", "str": " eine Anzeige wegen Tierq\u00e4lerei und K\u00f6rperverletzung gewiss."}, {"class": "strc", "str": "</p>"}], "hitlen": "", "Tbl_refs": ["coralian.de"], "linegroup": "_", "Kwic": [{"class": "col0 coll", "str": " Hundeguru"}], "ref": "coralian.de", "toknum": 12322821013, "Left": [{"class": "", "str": "Heute w\u00e4re dem"}]}, {"Right": [{"class": "", "str": "- der Name steht f\u00fcr eine \"neue\" Art des Coachings f\u00fcr Mensch mit Hund."}], "hitlen": "", "Tbl_refs": ["hunde-info-portal.de"], "linegroup": "_", "Kwic": [{"class": "col0 coll", "str": "Hundeguru"}], "ref": "hunde-info-portal.de", "toknum": 3022243010, "Left": [{"class": "strc", "str": "<p>"}]}, {"Right": [{"class": "", "str": " denkt was anderes - aber nur so entsteht eine Diskusion - wenn viele verschiedene Meinungen zusammen kommen, oder?"}, {"class": "strc", "str": "</p>"}], "hitlen": "", "Tbl_refs": ["tier-inserate.ch"], "linegroup": "_", "Kwic": [{"class": "col0 coll", "str": "Hundeguru"}], "ref": "tier-inserate.ch", "toknum": 3194110950, "Left": []}, {"Right": [{"class": "", "str": " vermittelt die F\u00e4higkeit, sich in Mensch und Hund hinein zu versetzen und damit gr\u00f6\u00dftm\u00f6gliche und dauerhafte Erfolge zu erzielen."}], "hitlen": "", "Tbl_refs": ["seminar-lotse.de"], "linegroup": "_", "Kwic": [{"class": "col0 coll", "str": "Hundeguru"}], "ref": "seminar-lotse.de", "toknum": 3988528816, "Left": []}, {"Right": [{"class": "", "str": "!"}], "hitlen": "", "Tbl_refs": ["hundezeitung.de"], "linegroup": "_", "Kwic": [{"class": "col0 coll", "str": " Hundeguru"}], "ref": "hundezeitung.de", "toknum": 19521812307, "Left": [{"class": "strc", "str": "<p>"}, {"class": "", "str": "Guten Tag, gestatten das ich mich vorstelle: Mein Name ist"}]}, {"Right": [{"class": "", "str": ": Die hat von Hunden auch keine Ahnung!"}, {"class": "strc", "str": "</p>"}], "hitlen": "", "Tbl_refs": ["tier-inserate.ch"], "linegroup": "_", "Kwic": [{"class": "col0 coll", "str": " Hundeguru"}], "ref": "tier-inserate.ch", "toknum": 6159811144, "Left": [{"class": "strc", "str": "<p>"}, {"class": "", "str": "Ich sags mal wie"}]}, {"Right": [{"class": "", "str": "\" in die \u00d6ffentlichkeit, der meint, das Rad neu erfunden zu haben."}], "hitlen": "", "Tbl_refs": ["angst-hund.de"], "linegroup": "_", "Kwic": [{"class": "col0 coll", "str": "Hundeguru"}], "ref": "angst-hund.de", "toknum": 5016440303, "Left": [{"class": "strc", "str": "<p>"}, {"class": "", "str": "Leider kommt immer mal wieder irgendein neuer \""}]}, {"Right": [{"class": "", "str": " oder Fl\u00fcsterer."}], "hitlen": "", "Tbl_refs": ["tierakademie-zischgl.de"], "linegroup": "_", "Kwic": [{"class": "col0 coll", "str": " Hundegurus"}], "ref": "tierakademie-zischgl.de", "toknum": 19274206615, "Left": [{"class": "strc", "str": "<p>"}, {"class": "", "str": "Allerdings warne ich vor sogenannten"}]}, {"Right": [{"class": "", "str": ", auf die auch viele Hundebesitzer schw\u00f6ren, ist das sogenannte Clickertraining."}], "hitlen": "", "Tbl_refs": ["hundewelt.info"], "linegroup": "_", "Kwic": [{"class": "col0 coll", "str": " Hundeguru"}], "ref": "hundewelt.info", "toknum": 9038133821, "Left": [{"class": "strc", "str": "<p>"}, {"class": "", "str": "Eine weitere Methode ohne"}]}, {"Right": [{"class": "", "str": " \u2013 es ging runter wie \u00d6l."}], "hitlen": "", "Tbl_refs": ["dogprofi.at"], "linegroup": "_", "Kwic": [{"class": "col0 coll", "str": " Hundegurus"}], "ref": "dogprofi.at", "toknum": 19519694226, "Left": [{"class": "", "str": "Das gr\u00f6\u00dfte Highlight an diesem Treffen war ein \"LOB\" aus dem Mund unseres"}]}, {"Right": [{"class": "", "str": "\" auch dort lebt, eher auch nicht mal kennt."}, {"class": "strc", "str": "</p>"}], "hitlen": "", "Tbl_refs": ["tier-inserate.ch"], "linegroup": "_", "Kwic": [{"class": "col0 coll", "str": "Hundeguru"}], "ref": "tier-inserate.ch", "toknum": 3194112933, "Left": [{"class": "strc", "str": "<p>"}, {"class": "", "str": "Kiribati ist ein Inselstaat im Pazifik und ich denke nicht dass \""}]}, {"Right": [{"class": "", "str": " verkaufen pauschale Erziehungsmethoden und sind nach 10 Einzelstunden nicht in der Lage, dem Hundehalter eine Leinenf\u00fchrigkeit zu vermitteln."}], "hitlen": "", "Tbl_refs": ["animal-health-online.de"], "linegroup": "_", "Kwic": [{"class": "col0 coll", "str": "Hundegurus"}], "ref": "animal-health-online.de", "toknum": 9194072397, "Left": []}, {"Right": [{"class": "", "str": "\" handelt, bei dem alle anderen Meinungen nicht gelten."}], "hitlen": "", "Tbl_refs": ["jagdnatur.ch"], "linegroup": "_", "Kwic": [{"class": "col0 coll", "str": " Hundeguru"}], "ref": "jagdnatur.ch", "toknum": 17876570142, "Left": [{"class": "", "str": "Noch schlimmer wird es, wenn es sich beim Gegen\u00fcber um einen \"richtigen"}]}, {"Right": [{"class": "", "str": " wie Cesar Millan, polarisiert, und seine Gegner machen mobil."}, {"class": "strc", "str": "</p>"}], "hitlen": "", "Tbl_refs": ["issnruede.de"], "linegroup": "_", "Kwic": [{"class": "col0 coll", "str": " Hundeguru"}], "ref": "issnruede.de", "toknum": 847945961, "Left": [{"class": "strc", "str": "<p>"}, {"class": "", "str": "Ein"}]}, {"Right": [{"class": "", "str": ", Hundeprofi, Hundefl\u00fcsterer oder eine Hundenanny sondern schlicht und einfach einen guten Hundetrainer!"}, {"class": "strc", "str": "</p>"}], "hitlen": "", "Tbl_refs": ["team-ideal.de"], "linegroup": "_", "Kwic": [{"class": "col0 coll", "str": " Hundeguru"}], "ref": "team-ideal.de", "toknum": 16433076251, "Left": [{"class": "strc", "str": "<p>"}, {"class": "", "str": "Sie brauchen keinen sogenannten"}]}, {"Right": [{"class": "", "str": " in den USA auch hier verursacht."}], "hitlen": "", "Tbl_refs": ["blogspot.de"], "linegroup": "_", "Kwic": [{"class": "col0 coll", "str": " Hundeguru"}], "ref": "blogspot.de", "toknum": 10006909649, "Left": [{"class": "strc", "str": "<p>"}, {"class": "", "str": "Und dennoch verwundert mich in der letzten Zeit die Aufregung in der Forenwelt, die ein selbsternannter"}]}, {"Right": [{"class": "", "str": " - Termine f\u00fcr Seminare, Workshops, Workinare Du liebst Hunde?"}], "hitlen": "", "Tbl_refs": ["seminar-lotse.de"], "linegroup": "_", "Kwic": [{"class": "col0 coll", "str": "Hundeguru"}], "ref": "seminar-lotse.de", "toknum": 3988528169, "Left": [{"class": "strc", "str": "<p>"}]}, {"Right": [{"class": "", "str": " - was ist das also?"}], "hitlen": "", "Tbl_refs": ["tier-inserate.ch"], "linegroup": "_", "Kwic": [{"class": "col0 coll", "str": " Hundeguru"}], "ref": "tier-inserate.ch", "toknum": 5648973448, "Left": [{"class": "strc", "str": "<p>"}, {"class": "", "str": "Erstellt am: 18.09.2009 : 14:57:59 Uhr Und genau das wollte"}]}, {"Right": [{"class": "", "str": "!"}, {"class": "strc", "str": "</p>"}], "hitlen": "", "Tbl_refs": ["tier-inserate.ch"], "linegroup": "_", "Kwic": [{"class": "col0 coll", "str": " Hundeguru"}], "ref": "tier-inserate.ch", "toknum": 3194108269, "Left": [{"class": "strc", "str": "<p>"}, {"class": "", "str": "Erstellt am: 11.09.2009 : 14:57:48 Uhr Hallo Simona und"}]}, {"Right": [{"class": "", "str": " aus Oberursel, Der Hundeprofi, Der Kommunikator, und viele weitere Superlative die einfach zutreffen."}], "hitlen": "", "Tbl_refs": ["diehundeschulen.de"], "linegroup": "_", "Kwic": [{"class": "col0 coll", "str": " Hundeguru"}], "ref": "diehundeschulen.de", "toknum": 16183137456, "Left": [{"class": "strc", "str": "<p>"}, {"class": "", "str": "Der"}]}, {"Right": [{"class": "", "str": "\" mit erhobenen Zeigefinger ein, der allen Ernstes jahrelang die These aufstellte: \"Hunde spielen nicht\"."}], "hitlen": "", "Tbl_refs": ["canin.de"], "linegroup": "_", "Kwic": [{"class": "col0 coll", "str": "Hundeguru"}], "ref": "canin.de", "toknum": 16549907349, "Left": [{"class": "", "str": "Aber dabei f\u00e4llt uns schon gleich der n\u00e4chste \""}]}, {"Right": [{"class": "", "str": " \"zertifizierte\" Trainer, die (und nur die) dazu autorisiert sind das geballte Wissen weiter zu geben."}, {"class": "strc", "str": "</p>"}], "hitlen": "", "Tbl_refs": ["angst-hund.de"], "linegroup": "_", "Kwic": [{"class": "col0 coll", "str": " Hundeguru"}], "ref": "angst-hund.de", "toknum": 5016440423, "Left": [{"class": "strc", "str": "<p>"}, {"class": "", "str": "Ach ja immer auch wieder gerne genommen sind vom"}]}, {"Right": [{"class": "", "str": " einige gute Trainer hervorgebracht, die sowohl in England, Irland, Italien, USA und \u00d6sterreich als eigenst\u00e4ndige Trainer t\u00e4tig sind."}, {"class": "strc", "str": "</p>"}], "hitlen": "", "Tbl_refs": ["hundemeldungen.de"], "linegroup": "_", "Kwic": [{"class": "col0 coll", "str": " Hundeguru"}], "ref": "hundemeldungen.de", "toknum": 14087305468, "Left": [{"class": "strc", "str": "<p>"}, {"class": "", "str": "Mittlerweile hat"}]}, {"Right": [{"class": "", "str": ", zum 2. die Vorstellung, dass es so sch\u00f6n einfach sein k\u00f6nnte, wenn da auch nur F\u00fcnkchen Wahrheit dran w\u00e4re!"}, {"class": "strc", "str": "</p>"}], "hitlen": "", "Tbl_refs": ["angst-hund.de"], "linegroup": "_", "Kwic": [{"class": "col0 coll", "str": " Hundegurus"}], "ref": "angst-hund.de", "toknum": 5016440271, "Left": [{"class": "", "str": "Zum 1. die Vorstellung des"}]}, {"Right": [{"class": "", "str": " sein, um vorauszusehen, dass meine Kurze mit jedem weiteren Workingtest ihr Entfernen von meinem Bein, w\u00e4hrend eines Walkups, weiter ausbauen wird."}], "hitlen": "", "Tbl_refs": ["glorialupi.de"], "linegroup": "_", "Kwic": [{"class": "col0 coll", "str": " Hundeguru"}], "ref": "glorialupi.de", "toknum": 4061875718, "Left": [{"class": "strc", "str": "<p>"}, {"class": "", "str": "Mensch muss kein"}]}, {"Right": [{"class": "", "str": " verbindet - Workinar in Stade (Mon, 12 May 2008 14:38:41 +0200) Wer w\u00fcnscht sich nicht einen Lassy oder Rex?"}], "hitlen": "", "Tbl_refs": ["rss-nachrichten.de"], "linegroup": "_", "Kwic": [{"class": "col0 coll", "str": "Hundeguru"}], "ref": "rss-nachrichten.de", "toknum": 4067220550, "Left": [{"class": "strc", "str": "<p>"}]}, {"Right": [{"class": "", "str": " mit Sendungsbewusstsein."}], "hitlen": "", "Tbl_refs": ["movienerd.de"], "linegroup": "_", "Kwic": [{"class": "col0 coll", "str": " Hundeguru"}], "ref": "movienerd.de", "toknum": 12150731766, "Left": [{"class": "", "str": "Hinzu kommt apartes Schauspiel von der zu Unrecht verschm\u00e4hten Reservebank des US-Fernsehens, allen voran William Fichtner ( Prison Break ) als exzentrischer"}]}, {"Right": [{"class": "", "str": " Michael Grewe, unter Mitwirkung von Dr. Erik Zimen gegr\u00fcndet wurde."}], "hitlen": "", "Tbl_refs": ["ikamani.de"], "linegroup": "_", "Kwic": [{"class": "col0 coll", "str": " Hundeguru"}], "ref": "ikamani.de", "toknum": 11415667574, "Left": [{"class": "strc", "str": "<p>"}, {"class": "", "str": "Es handelt sich bei dieser Hundeschule um das Canis Zentrum f\u00fcr Kynologie, welches im Jahre 2002 durch den selbsternannten"}]}, {"Right": [{"class": "", "str": "."}], "hitlen": "", "Tbl_refs": ["hundezeitung.de"], "linegroup": "_", "Kwic": [{"class": "col0 coll", "str": " Hundeguru"}], "ref": "hundezeitung.de", "toknum": 19521812339, "Left": [{"class": "", "str": "Mich den"}]}, {"Right": [{"class": "", "str": " oder gar Hundefl\u00fcsterer, die immer noch Felsenfest auf der Dominanztheorie beharren, genau mit jenem kleinen Hilfsmittelchen arbeiten."}], "hitlen": "", "Tbl_refs": ["lebenmithund.at"], "linegroup": "_", "Kwic": [{"class": "col0 coll", "str": " Hundegurus"}], "ref": "lebenmithund.at", "toknum": 18822439278, "Left": [{"class": "strc", "str": "<p>"}, {"class": "", "str": "Wieder sind wir bei den Hundetrainern und wieder ist es \u00e4u\u00dferst interessant zu beobachten, dass genau diese Trainer, Psychologen,"}]}, {"Right": [{"class": "", "str": " \u0301s lernt, vermieden."}, {"class": "strc", "str": "</p>"}], "hitlen": "", "Tbl_refs": ["vomlupusforst.de"], "linegroup": "_", "Kwic": [{"class": "col0 coll", "str": " Hundeguru"}], "ref": "vomlupusforst.de", "toknum": 1117125504, "Left": [{"class": "strc", "str": "<p>"}, {"class": "", "str": "Ein schriftlicher Leitfaden f\u00fcr die ersten Monate zum Thema Schleppe, Appell, st\u00f6bern im Revier, frei werden lassen, h\u00e4tte mir es noch leichter gemacht und einige Fehler, die man von den einschl\u00e4gigen"}]}, {"Right": [{"class": "", "str": " ist anders."}], "hitlen": "", "Tbl_refs": ["seminar-lotse.de"], "linegroup": "_", "Kwic": [{"class": "col0 coll", "str": "Hundeguru"}], "ref": "seminar-lotse.de", "toknum": 3988528522, "Left": []}, {"Right": [{"class": "", "str": "...."}], "hitlen": "", "Tbl_refs": ["hundeschule-ab.de"], "linegroup": "_", "Kwic": [{"class": "col0 coll", "str": " Hundegurus"}], "ref": "hundeschule-ab.de", "toknum": 5359646304, "Left": [{"class": "", "str": "Zum anderen ist es leider fast immer \"alter Wein in neuen Schl\u00e4uchen\".. so wie das letzte, hochgelobte Buch eines selbsternannten"}]}, {"Right": [{"class": "", "str": " ist, bringt die Threaderstellerin nicht weiter."}, {"class": "strc", "str": "</p>"}], "hitlen": "", "Tbl_refs": ["jagdhundehalter.de"], "linegroup": "_", "Kwic": [{"class": "col0 coll", "str": " Hundeguru"}], "ref": "jagdhundehalter.de", "toknum": 1086711153, "Left": [{"class": "strc", "str": "<p>"}, {"class": "", "str": "Ich glaube, die Frage, wer der gr\u00f6\u00dfere Hundegro\u00dfko** ..\u00e4h,"}]}, {"Right": [{"class": "", "str": "- KOMMunikation kommt an..."}], "hitlen": "", "Tbl_refs": ["hunde.de"], "linegroup": "_", "Kwic": [{"class": "col0 coll", "str": "Hundeguru"}], "ref": "hunde.de", "toknum": 7819549430, "Left": [{"class": "strc", "str": "<p>"}]}, {"Right": [{"class": "", "str": " es bietet, hat nichts mehr zu tun mit Kommandos, sinnlosen Auf-dem-Platz-\u00dcbungen, nichts mit Dominanz oder Alpharolle des Menschen."}], "hitlen": "", "Tbl_refs": ["beepworld.de"], "linegroup": "_", "Kwic": [{"class": "col0 coll", "str": " Hundeguru"}], "ref": "beepworld.de", "toknum": 2663078316, "Left": [{"class": "", "str": "Ganzheitliches Training, wie"}]}, {"Right": [{"class": "", "str": " (wie er sich selbst nennt) wei\u00df keine weiteren Erziehungstipps und meldet sich einfach nicht mehr..."}, {"class": "strc", "str": "</p>"}], "hitlen": "", "Tbl_refs": ["aspa-ev.de"], "linegroup": "_", "Kwic": [{"class": "col0 coll", "str": " Hundeguru"}], "ref": "aspa-ev.de", "toknum": 7070515239, "Left": [{"class": "", "str": "Die Probleme werden nicht besser, im Gegenteil, es kommt zu ernsthaften Verletzungen untereinander - der"}]}, {"Right": [{"class": "", "str": ", was bist denn du f\u00fcr eine/r ??? In einem andern Thread hast du schon doof herumgemotzt und meintest du seist der gr\u00f6sste!"}], "hitlen": "", "Tbl_refs": ["tier-inserate.ch"], "linegroup": "_", "Kwic": [{"class": "col0 coll", "str": "Hundeguru"}], "ref": "tier-inserate.ch", "toknum": 8540332205, "Left": [{"class": "strc", "str": "<p>"}, {"class": "", "str": "Erstellt am: 07.09.2009 : 23:08:42 Uhr @"}]}, {"Right": [{"class": "", "str": "..."}], "hitlen": "", "Tbl_refs": ["hundeliebe-hundeschule.de"], "linegroup": "_", "Kwic": [{"class": "col0 coll", "str": " Hundeguru"}], "ref": "hundeliebe-hundeschule.de", "toknum": 1292877028, "Left": [{"class": "strc", "str": "<p>"}, {"class": "", "str": "Unser neuer"}]}, {"Right": [{"class": "strc", "str": "</p>"}], "hitlen": "", "Tbl_refs": ["tier-inserate.ch"], "linegroup": "_", "Kwic": [{"class": "col0 coll", "str": "Hundeguru"}], "ref": "tier-inserate.ch", "toknum": 5716943804, "Left": [{"class": "strc", "str": "<p>"}]}, {"Right": [{"class": "", "str": ": Es w\u00e4re angenehm wenn Du deinen Standpunkt verdeutlichen w\u00fcrdest, anstelle zur\u00fcck zu povozieren."}, {"class": "strc", "str": "</p>"}], "hitlen": "", "Tbl_refs": ["tier-inserate.ch"], "linegroup": "_", "Kwic": [{"class": "col0 coll", "str": "Hundeguru"}], "ref": "tier-inserate.ch", "toknum": 3194108412, "Left": [{"class": "", "str": "Manchmal lohnt sich deswegen eine Diskussion leider gar nicht, weil es bereits auf der Ebene der Verst\u00e4ndnisbereitschaft happert! @Simona:Ich verstehe aus den genannten Gr\u00fcnden nicht, weshalb Du, Simona, gleich so agressiv und doch eher ausf\u00e4llig auf die Bemerkung von Hundeguru reagierst! @"}]}, {"Right": [{"class": "", "str": "[/i] [br]Rottweiler schnappen auch nicht nach Kindern, wenn man sie vern\u00fcnftig aufzieht und trainiert, das bitte la\u00dft euch mal von mir hier gesagt sein, oder ihr habt von Hunde keine Ahnung [/quote]"}, {"class": "strc", "str": "</p>"}], "hitlen": "", "Tbl_refs": ["tier-inserate.ch"], "linegroup": "_", "Kwic": [{"class": "col0 coll", "str": " Hundeguru"}], "ref": "tier-inserate.ch", "toknum": 5716943292, "Left": [{"class": "strc", "str": "<p>"}, {"class": "", "str": "[quote][i]Original erstellt von:"}]}, {"Right": [{"class": "", "str": ", die ihre Methode als alleinseeligmachend hinstellen und dene die Leute das Geld in S\u00e4cken hintragen, blind daf\u00fcr, dass ihre Hunde nach diesen in Liebe verpackten Gewalttaten nur noch beschwichtigend dahertrotten."}, {"class": "strc", "str": "</p>"}], "hitlen": "", "Tbl_refs": ["blogspot.de"], "linegroup": "_", "Kwic": [{"class": "col0 coll", "str": " Hundegurus"}], "ref": "blogspot.de", "toknum": 7888152041, "Left": [{"class": "strc", "str": "<p>"}, {"class": "", "str": "Ich hoffe,das Pr\u00e4dikat bekommen auch die Schlauchwerfer, Zischer und andere perfide selbsternannte"}]}, {"Right": [{"class": "", "str": " einverstanden Chihuahuas sind so klein dass, sie perfekt im Berufsleben passen, frag mal deinen Chef ob er einverstanden w\u00e4re, dass der Hund mikommt und schon ist das Problem gel\u00f6st."}], "hitlen": "", "Tbl_refs": ["tier-inserate.ch"], "linegroup": "_", "Kwic": [{"class": "col0 coll", "str": " Hundeguru"}], "ref": "tier-inserate.ch", "toknum": 2925522835, "Left": [{"class": "strc", "str": "<p>"}, {"class": "", "str": "Erstellt am: 20.09.2009 : 17:48:58 Uhr ich bin mit dem"}]}, {"Right": [{"class": "strc", "str": "</p>"}], "hitlen": "", "Tbl_refs": ["tier-inserate.ch"], "linegroup": "_", "Kwic": [{"class": "col0 coll", "str": "Hundeguru"}], "ref": "tier-inserate.ch", "toknum": 6159811283, "Left": [{"class": "strc", "str": "<p>"}]}, {"Right": [{"class": "strc", "str": "</p>"}], "hitlen": "", "Tbl_refs": ["tier-inserate.ch"], "linegroup": "_", "Kwic": [{"class": "col0 coll", "str": "Hundeguru"}], "ref": "tier-inserate.ch", "toknum": 3194107817, "Left": [{"class": "strc", "str": "<p>"}]}, {"Right": [{"class": "strc", "str": "</p>"}], "hitlen": "", "Tbl_refs": ["tier-inserate.ch"], "linegroup": "_", "Kwic": [{"class": "col0 coll", "str": "Hundeguru"}], "ref": "tier-inserate.ch", "toknum": 3194110433, "Left": [{"class": "strc", "str": "<p>"}]}, {"Right": [{"class": "strc", "str": "</p>"}], "hitlen": "", "Tbl_refs": ["tier-inserate.ch"], "linegroup": "_", "Kwic": [{"class": "col0 coll", "str": "Hundeguru"}], "ref": "tier-inserate.ch", "toknum": 3194112729, "Left": [{"class": "strc", "str": "<p>"}]}, {"Right": [{"class": "strc", "str": "</p>"}], "hitlen": "", "Tbl_refs": ["tier-inserate.ch"], "linegroup": "_", "Kwic": [{"class": "col0 coll", "str": "Hundeguru"}], "ref": "tier-inserate.ch", "toknum": 8540332260, "Left": [{"class": "strc", "str": "<p>"}]}, {"Right": [{"class": "strc", "str": "</p>"}], "hitlen": "", "Tbl_refs": ["tier-inserate.ch"], "linegroup": "_", "Kwic": [{"class": "col0 coll", "str": "Hundeguru"}], "ref": "tier-inserate.ch", "toknum": 3194110720, "Left": [{"class": "strc", "str": "<p>"}]}, {"Right": [{"class": "strc", "str": "</p>"}], "hitlen": "", "Tbl_refs": ["tier-inserate.ch"], "linegroup": "_", "Kwic": [{"class": "col0 coll", "str": "Hundeguru"}], "ref": "tier-inserate.ch", "toknum": 8540332318, "Left": [{"class": "strc", "str": "<p>"}]}, {"Right": [{"class": "strc", "str": "</p>"}], "hitlen": "", "Tbl_refs": ["tier-inserate.ch"], "linegroup": "_", "Kwic": [{"class": "col0 coll", "str": "Hundeguru"}], "ref": "tier-inserate.ch", "toknum": 10617078425, "Left": [{"class": "strc", "str": "<p>"}]}, {"Right": [{"class": "strc", "str": "</p>"}], "hitlen": "", "Tbl_refs": ["tier-inserate.ch"], "linegroup": "_", "Kwic": [{"class": "col0 coll", "str": "Hundeguru"}], "ref": "tier-inserate.ch", "toknum": 8540332149, "Left": [{"class": "strc", "str": "<p>"}]}, {"Right": [{"class": "strc", "str": "</p>"}], "hitlen": "", "Tbl_refs": ["tier-inserate.ch"], "linegroup": "_", "Kwic": [{"class": "col0 coll", "str": "Hundeguru"}], "ref": "tier-inserate.ch", "toknum": 5716943489, "Left": [{"class": "strc", "str": "<p>"}]}, {"Right": [{"class": "strc", "str": "</p>"}], "hitlen": "", "Tbl_refs": ["tier-inserate.ch"], "linegroup": "_", "Kwic": [{"class": "col0 coll", "str": "Hundeguru"}], "ref": "tier-inserate.ch", "toknum": 5716943671, "Left": [{"class": "strc", "str": "<p>"}]}, {"Right": [{"class": "strc", "str": "</p>"}], "hitlen": "", "Tbl_refs": ["tier-inserate.ch"], "linegroup": "_", "Kwic": [{"class": "col0 coll", "str": "Hundeguru"}], "ref": "tier-inserate.ch", "toknum": 3194110060, "Left": [{"class": "strc", "str": "<p>"}]}, {"Right": [{"class": "strc", "str": "</p>"}], "hitlen": "", "Tbl_refs": ["tier-inserate.ch"], "linegroup": "_", "Kwic": [{"class": "col0 coll", "str": "Hundeguru"}], "ref": "tier-inserate.ch", "toknum": 5648973071, "Left": [{"class": "strc", "str": "<p>"}]}, {"Right": [{"class": "", "str": " reagierst! @Hundeguru: Es w\u00e4re angenehm wenn Du deinen Standpunkt verdeutlichen w\u00fcrdest, anstelle zur\u00fcck zu povozieren."}, {"class": "strc", "str": "</p>"}], "hitlen": "", "Tbl_refs": ["tier-inserate.ch"], "linegroup": "_", "Kwic": [{"class": "col0 coll", "str": " Hundeguru"}], "ref": "tier-inserate.ch", "toknum": 3194108408, "Left": [{"class": "", "str": "Manchmal lohnt sich deswegen eine Diskussion leider gar nicht, weil es bereits auf der Ebene der Verst\u00e4ndnisbereitschaft happert! @Simona:Ich verstehe aus den genannten Gr\u00fcnden nicht, weshalb Du, Simona, gleich so agressiv und doch eher ausf\u00e4llig auf die Bemerkung von"}]}, {"Right": [{"class": "strc", "str": "</p>"}], "hitlen": "", "Tbl_refs": ["tier-inserate.ch"], "linegroup": "_", "Kwic": [{"class": "col0 coll", "str": "Hundeguru"}], "ref": "tier-inserate.ch", "toknum": 2925523900, "Left": [{"class": "strc", "str": "<p>"}]}, {"Right": [{"class": "strc", "str": "</p>"}], "hitlen": "", "Tbl_refs": ["tier-inserate.ch"], "linegroup": "_", "Kwic": [{"class": "col0 coll", "str": "Hundeguru"}], "ref": "tier-inserate.ch", "toknum": 2708613129, "Left": [{"class": "strc", "str": "<p>"}]}], "request": {"username": "spahic", "gdex_enabled": "1", "pagesize": "200", "format": "json", "lpos": "-n", "q": "q[lemma=\"Hundeguru\"]", "viewmode": "sentence", "async": "0", "corpname": "detenten13_rft3", "api_key": "159b841f61a64092bc630d20b0f56c93"}, "q": ["q[lemma=\"Hundeguru\"]", "e100 "], "righttoleft": false, "finished": 1, "relsize": 0.0, "gdex_scores": {"1117125504": 0.5, "3194110720": 0.0, "7888152041": 0.0, "3194112729": 0.0, "4061875718": 0.5866666666666667, "5716943489": 0.0, "5648973448": 0.6840909090909091, "2708613129": 0.0, "3988528522": 0.5, "5648973071": 0.0, "3194107817": 0.0, "19519694226": 0.7522282608695651, "2925522835": 0.0, "12322821013": 0.7916666666666667, "19274206615": 0.7666666666666667, "10617078425": 0.0, "16433076251": 0.70625, "17876570142": 0.7187499999999999, "14087305247": 0.8033333333333332, "16183137456": 0.6684210526315789, "8540332260": 0.0, "3194112933": 0.7449999999999999, "7070515239": 0.03777777777777778, "3988528169": 0.6903846153846154, "13476125511": 0.8666666666666667, "2663078316": 0.0968981481481481, "8540332205": 0.007628205128205137, "1812112430": 0.828125, "3988528816": 0.7792045454545453, "7819549430": 0.13333333333333333, "8540332318": 0.0, "5716943671": 0.0, "5716943804": 0.0, "7949441981": 0.8529411764705883, "8540332149": 0.0, "3022243010": 0.7833333333333334, "7819549509": 0.8033333333333332, "4067220550": 0.5642857142857143, "19116914759": 0.8515625, "6159811144": 0.7785714285714285, "6159811283": 0.0, "2010817995": 0.80625, "9194072397": 0.7307142857142859, "5016440271": 0.6024137931034482, "10006909649": 0.6980000000000001, "19521812307": 0.7785714285714285, "2925523900": 0.0, "14087305302": 0.8477272727272728, "5016440025": 0.8325, "3194108412": 0.0, "5359646304": 0.1857692307692307, "3194110433": 0.0, "1292877028": 0.0, "3194110950": 0.7793452380952383, "5016440423": 0.6262903225806451, "19553155305": 0.8157894736842104, "3194110060": 0.0, "3194108269": 0.6828125, "18822439278": 0.5, "5016440303": 0.7683333333333331, "5716943292": 0.0, "1086711153": 0.16630434782608688, "19521812339": 0.5, "10006909940": 0.828125, "11415667574": 0.5296969696969697, "12150731766": 0.5541666666666667, "847945961": 0.7142857142857142, "3194108408": 0.0, "14087305468": 0.6177884615384615, "9038133821": 0.7666666666666667, "16549907349": 0.6283333333333334}, "Desc": [{"nicearg": "Hundeguru", "tourl": "q=q%5Blemma%3D%22Hundeguru%22%5D", "rel": 0.0, "arg": "[lemma=\"Hundeguru\"]", "op": "Query", "size": 71}, {"nicearg": "", "tourl": "q=q%5Blemma%3D%22Hundeguru%22%5D&q=e100+", "rel": 0.0, "arg": "100 ", "op": "GDEX", "size": 71}], "concsize": 71, "port": 0, "api_version": "3.112.9", "fullsize": 71}