{"Sort_idx": [], "sc_strcts": [["doc", "doc"], ["p", "p"], ["s", "s"], ["g", "g"]], "Lines": [{"Right": [{"class": "", "str": " mit Pr\u00e4dikat f\u00fcr die, die es sich verdient haben und es sich leisten k\u00f6nnen, auf hohem Niveau \u00fcber andere zu lachen\"."}], "hitlen": "", "Tbl_refs": ["schreibwolff.de"], "linegroup": "_", "Kwic": [{"class": "col0 coll", "str": "Qualit\u00e4tswitze"}], "ref": "schreibwolff.de", "toknum": 15480170108, "Left": [{"class": "strc", "str": "<p>"}, {"class": "", "str": "Angek\u00fcndigt werden \""}]}, {"Right": [{"class": "", "str": " mit Pr\u00e4dikat"}, {"class": "strc", "str": "</p>"}], "hitlen": "", "Tbl_refs": ["schreibwolff.de"], "linegroup": "_", "Kwic": [{"class": "col0 coll", "str": " Qualit\u00e4tswitze"}], "ref": "schreibwolff.de", "toknum": 15479835445, "Left": [{"class": "strc", "str": "<p>"}, {"class": "", "str": "Kabarett \"M\u00e4nnerKulturen\" bietet"}]}, {"Right": [{"class": "", "str": " mit Pr\u00e4dikat\" verk\u00fcndet dasHerren-Trio f\u00fcr die Zukunft und fragt verschmitzt: \"Soll ich meinem Hund die Vertrauensfrage stellen?"}], "hitlen": "", "Tbl_refs": ["pantheon.de"], "linegroup": "_", "Kwic": [{"class": "col0 coll", "str": "Qualit\u00e4tswitze"}], "ref": "pantheon.de", "toknum": 12464058817, "Left": []}, {"Right": [{"class": "", "str": " unter www.stephanruerup.de!) \u2013 der nebenstehende Cartoon vorbildlich die Vorz\u00fcge aus Frauensicht, bei Misswahl oder Mogelpackung oder Haltbarkeits\u00fcberschreitung von der unkomplizierten R\u00fcckgabe regen Gebrauch zu machen (denkbare Empfehlung hier wie bei Amazon: Frauen, die diesen Kerl umtauschten, raten auch von diesen Versagern ab ->)."}, {"class": "strc", "str": "</p>"}], "hitlen": "", "Tbl_refs": ["garbersgazette.de"], "linegroup": "_", "Kwic": [{"class": "col0 coll", "str": " Qualit\u00e4tswitze"}], "ref": "garbersgazette.de", "toknum": 2746080684, "Left": [{"class": "", "str": "Und sicher trifft \u2013 gro\u00dfer Dank f\u00fcr die Genehmigung zur hiesigen Ver\u00f6ffentlichung an den zeichnenden Kollegen und Gro\u00dfmeister Stephan R\u00fcrup (Empfehlung: Kaufen Sie"}]}], "request": {"username": "spahic", "gdex_enabled": "1", "pagesize": "200", "format": "json", "lpos": "-n", "q": "q[lemma=\"Qualit\u00e4tswitze\"]", "viewmode": "sentence", "async": "0", "corpname": "detenten13_rft3", "api_key": "159b841f61a64092bc630d20b0f56c93"}, "q": ["q[lemma=\"Qualit\u00e4tswitze\"]", "e100 "], "righttoleft": false, "finished": 1, "relsize": 0.0, "gdex_scores": {"12464058817": 0.2025, "2746080684": 0.0, "15480170108": 0.6664224137931033, "15479835445": 0.3}, "Desc": [{"nicearg": "Qualit\u00e4tswitze", "tourl": "q=q%5Blemma%3D%22Qualit%C3%A4tswitze%22%5D", "rel": 0.0, "arg": "[lemma=\"Qualit\u00e4tswitze\"]", "op": "Query", "size": 4}, {"nicearg": "", "tourl": "q=q%5Blemma%3D%22Qualit%C3%A4tswitze%22%5D&q=e100+", "rel": 0.0, "arg": "100 ", "op": "GDEX", "size": 4}], "concsize": 4, "port": 0, "api_version": "3.112.9", "fullsize": 4}