{"Sort_idx": [], "sc_strcts": [["doc", "doc"], ["p", "p"], ["s", "s"], ["g", "g"]], "Lines": [{"Right": [{"class": "", "str": " erleben."}, {"class": "strc", "str": "</p>"}], "hitlen": "", "Tbl_refs": ["gc-heddesheim.de"], "linegroup": "_", "Kwic": [{"class": "col0 coll", "str": " Spitzengolf"}], "ref": "gc-heddesheim.de", "toknum": 15673400276, "Left": [{"class": "", "str": "Hier kann jeder kostenlos zuschauen und"}]}, {"Right": [{"class": "", "str": "!"}], "hitlen": "", "Tbl_refs": ["golfakademie-gmbh.de"], "linegroup": "_", "Kwic": [{"class": "col0 coll", "str": " Spitzengolf"}], "ref": "golfakademie-gmbh.de", "toknum": 8138931, "Left": [{"class": "", "str": "Er zeigte bei diesem verr\u00fcckten Wetter"}]}, {"Right": [{"class": "", "str": " zu spielen."}, {"class": "strc", "str": "</p>"}], "hitlen": "", "Tbl_refs": ["spicygolfforum.de"], "linegroup": "_", "Kwic": [{"class": "col0 coll", "str": " Spitzengolf"}], "ref": "spicygolfforum.de", "toknum": 633379404, "Left": [{"class": "", "str": "Aber eben auch eine M\u00c3\u00b6glichkeit,"}]}, {"Right": [{"class": "", "str": "."}], "hitlen": "", "Tbl_refs": ["golfakademie-gmbh.de"], "linegroup": "_", "Kwic": [{"class": "col0 coll", "str": " Spitzengolf"}], "ref": "golfakademie-gmbh.de", "toknum": 19566866611, "Left": [{"class": "", "str": "Das Wetter war nahezu perfekt und die Spieler zeigten"}]}, {"Right": [{"class": "", "str": " f\u00fcr alle."}], "hitlen": "", "Tbl_refs": ["gck.ch"], "linegroup": "_", "Kwic": [{"class": "col0 coll", "str": " Spitzengolf"}], "ref": "gck.ch", "toknum": 14229572901, "Left": [{"class": "", "str": "Nach dem Motto viel Spass und"}]}, {"Right": [{"class": "", "str": "?"}], "hitlen": "", "Tbl_refs": ["golfforum.de"], "linegroup": "_", "Kwic": [{"class": "col0 coll", "str": " Spitzengolf"}], "ref": "golfforum.de", "toknum": 965810168, "Left": [{"class": "", "str": "Es stellt sich die Frage, wie viel Fitness braucht man f\u00fcr"}]}, {"Right": [{"class": "", "str": " traditionell den Kontinent."}], "hitlen": "", "Tbl_refs": ["golfsport-faq.de"], "linegroup": "_", "Kwic": [{"class": "col0 coll", "str": " Spitzengolfs"}], "ref": "golfsport-faq.de", "toknum": 13815711479, "Left": [{"class": "strc", "str": "<p>"}, {"class": "", "str": "Im Sp\u00e4therbst wechselt die Welt des"}]}, {"Right": [{"class": "", "str": " gelehrt wird."}], "hitlen": "", "Tbl_refs": ["golfclub-schwanhof.de"], "linegroup": "_", "Kwic": [{"class": "col0 coll", "str": " Spitzengolf"}], "ref": "golfclub-schwanhof.de", "toknum": 13842782669, "Left": [{"class": "", "str": "Sie stehen daf\u00fcr, dass in Schwanhof"}]}, {"Right": [{"class": "", "str": " sind Entfernungsmesser seit Jahren nicht mehr wegzudenken."}], "hitlen": "", "Tbl_refs": ["golflaser.de"], "linegroup": "_", "Kwic": [{"class": "col0 coll", "str": " Spitzengolf"}], "ref": "golflaser.de", "toknum": 14211627232, "Left": [{"class": "strc", "str": "<p>"}, {"class": "", "str": "Im"}]}, {"Right": [{"class": "", "str": " herangef\u00c31\u20444hrt werden k\u00c3\u00b6nnen."}], "hitlen": "", "Tbl_refs": ["golfforum.de"], "linegroup": "_", "Kwic": [{"class": "col0 coll", "str": " Spitzengolf"}], "ref": "golfforum.de", "toknum": 12904187475, "Left": [{"class": "", "str": "Es geht um den Weg, wie Kinder und Jugendliche zum"}]}, {"Right": [{"class": "", "str": " in Deutschland macht, befindet sich definitiv auf dem Holzweg."}], "hitlen": "", "Tbl_refs": ["golfforum.de"], "linegroup": "_", "Kwic": [{"class": "col0 coll", "str": " Spitzengolf"}], "ref": "golfforum.de", "toknum": 965810325, "Left": [{"class": "", "str": "Wer aber daraus eine Philosophie f\u00fcr das"}]}, {"Right": [{"class": "", "str": "."}], "hitlen": "", "Tbl_refs": ["golfforum.de"], "linegroup": "_", "Kwic": [{"class": "col0 coll", "str": " Spitzengolf"}], "ref": "golfforum.de", "toknum": 965809586, "Left": [{"class": "", "str": "Der RTP befindet sich Abseits jeglicher Realit\u00e4t zum erfolgreichen"}]}, {"Right": [{"class": "", "str": " geht nur mit den Eltern."}], "hitlen": "", "Tbl_refs": ["golfforum.de"], "linegroup": "_", "Kwic": [{"class": "col0 coll", "str": " Spitzengolf"}], "ref": "golfforum.de", "toknum": 9445195763, "Left": [{"class": "strc", "str": "<p>"}, {"class": "", "str": "Fred: Erfolgreiches"}]}, {"Right": [{"class": "", "str": " als Helfer oder Helferin."}], "hitlen": "", "Tbl_refs": ["creditsuisse-challenge.ch"], "linegroup": "_", "Kwic": [{"class": "col0 coll", "str": " Spitzengolf"}], "ref": "creditsuisse-challenge.ch", "toknum": 10578186073, "Left": [{"class": "", "str": "Erleben Sie europ\u00e4isches"}]}, {"Right": [{"class": "", "str": " herausragende mentale und k\u00c3\u00b6rperliche F\u00c3\u00a4higkeiten."}], "hitlen": "", "Tbl_refs": ["golfanfangen.de"], "linegroup": "_", "Kwic": [{"class": "col0 coll", "str": " Spitzengolf"}], "ref": "golfanfangen.de", "toknum": 9742003820, "Left": [{"class": "strc", "str": "<p>"}, {"class": "", "str": "Nat\u00c31\u20444rlich brauchen Sie f\u00c31\u20444r den Weg zum"}]}, {"Right": [{"class": "", "str": ", und wir meinen in diesem Fall Profi Golf, weckt das Interesse der \u00c3\u2013ffentlichkeit."}], "hitlen": "", "Tbl_refs": ["golfforum.de"], "linegroup": "_", "Kwic": [{"class": "col0 coll", "str": "Spitzengolf"}], "ref": "golfforum.de", "toknum": 9438465237, "Left": []}, {"Right": [{"class": "", "str": " weiter fort."}], "hitlen": "", "Tbl_refs": ["golfsportmagazin.de"], "linegroup": "_", "Kwic": [{"class": "col0 coll", "str": " Spitzengolfs"}], "ref": "golfsportmagazin.de", "toknum": 11544274815, "Left": [{"class": "", "str": "Mit der Weiterentwicklung einer deutschlandweit vorbildlichen Trainingsinfrastruktur setzt der Club seinen Kurs zur F\u00f6rderung des"}]}, {"Right": [{"class": "", "str": " wird erst aus der N\u00e4he wirklich erfahrbar."}], "hitlen": "", "Tbl_refs": ["golfjournal.de"], "linegroup": "_", "Kwic": [{"class": "col0 coll", "str": " Spitzengolf"}], "ref": "golfjournal.de", "toknum": 3628102049, "Left": [{"class": "", "str": "F\u00fcr Sportinteressierte ist diese Direktheit unbezahlbar, denn"}]}, {"Right": [{"class": "", "str": "."}], "hitlen": "", "Tbl_refs": ["bayerischer-golfverband.de"], "linegroup": "_", "Kwic": [{"class": "col0 coll", "str": " Spitzengolf"}], "ref": "bayerischer-golfverband.de", "toknum": 3804931163, "Left": [{"class": "strc", "str": "<p>"}, {"class": "", "str": "Die Jungen zeigten auf dem anspruchsvollen Championship Course Golf"}]}, {"Right": [{"class": "", "str": " geh\u00f6ren."}], "hitlen": "", "Tbl_refs": ["golfmagazin.de"], "linegroup": "_", "Kwic": [{"class": "col0 coll", "str": " Spitzengolfs"}], "ref": "golfmagazin.de", "toknum": 11534573963, "Left": [{"class": "strc", "str": "<p>"}, {"class": "", "str": "L\u00e4ngst ist es Tradition, dass die Clubmannschaften zum Establishment des deutschen"}]}, {"Right": [{"class": "", "str": " in Abenberg."}], "hitlen": "", "Tbl_refs": ["golfclubabenberg.de"], "linegroup": "_", "Kwic": [{"class": "col0 coll", "str": " Spitzengolf"}], "ref": "golfclubabenberg.de", "toknum": 11794566027, "Left": [{"class": "", "str": "Es wird bei uns das Ligafinale ausgetragen, das hei\u00dft:"}]}, {"Right": [{"class": "", "str": " auf der europ\u00e4ischen Tour."}], "hitlen": "", "Tbl_refs": ["sky.de"], "linegroup": "_", "Kwic": [{"class": "col0 coll", "str": " Spitzengolf"}], "ref": "sky.de", "toknum": 13171952594, "Left": [{"class": "strc", "str": "<p>"}, {"class": "", "str": "Bereits ab dem 6. Januar kommen Sky Abonnenten in den Genuss von"}]}, {"Right": [{"class": "", "str": "."}], "hitlen": "", "Tbl_refs": ["golfteamgermany.de"], "linegroup": "_", "Kwic": [{"class": "col0 coll", "str": " Spitzengolf"}], "ref": "golfteamgermany.de", "toknum": 12324102842, "Left": [{"class": "", "str": "Im Eiltempo hat sich die 23-J\u00e4hrige mit den blauen Augen und den dunklen Haaren einen Namen gemacht im europ\u00e4ischen"}]}, {"Right": [{"class": "", "str": ", exzellente Organisation und eine besondere Atmosph\u00e4re."}], "hitlen": "", "Tbl_refs": ["golfmagazin.de"], "linegroup": "_", "Kwic": [{"class": "col0 coll", "str": " Spitzengolf"}], "ref": "golfmagazin.de", "toknum": 3456457641, "Left": [{"class": "strc", "str": "<p>"}, {"class": "", "str": "Seit 22 Jahren stehen die BMW International Open f\u00fcr internationales"}]}, {"Right": [{"class": "", "str": " werfen, denn es gibt etwas, das mir sehr am Herzen liegt."}], "hitlen": "", "Tbl_refs": ["bergedorfer-zeitung.de"], "linegroup": "_", "Kwic": [{"class": "col0 coll", "str": " Spitzengolf"}], "ref": "bergedorfer-zeitung.de", "toknum": 8010373296, "Left": [{"class": "", "str": "Dennoch m\u00f6chte ich den Blick zuvor gerne einmal weg vom"}]}, {"Right": [{"class": "", "str": " vom Feinsten."}], "hitlen": "", "Tbl_refs": ["gck.ch"], "linegroup": "_", "Kwic": [{"class": "col0 coll", "str": " Spitzengolf"}], "ref": "gck.ch", "toknum": 9351953370, "Left": [{"class": "", "str": "In den Einzel am Nachmittag zeigten die Spieler von K\u00fcssnacht gegen hervorragende Ennetseer"}]}, {"Right": [{"class": "", "str": ", eine exzellente Organisation und eine besonders angenehme, famili\u00e4re Atmosph\u00e4re."}], "hitlen": "", "Tbl_refs": ["golfnrw-online.de"], "linegroup": "_", "Kwic": [{"class": "col0 coll", "str": " Spitzengolf"}], "ref": "golfnrw-online.de", "toknum": 12902624946, "Left": [{"class": "", "str": "Nicht umsonst steht das Turnier seit 22 Jahren f\u00fcr internationales"}]}, {"Right": [{"class": "", "str": " durchaus sinnig ist."}], "hitlen": "", "Tbl_refs": ["golfforum.de"], "linegroup": "_", "Kwic": [{"class": "col0 coll", "str": " Spitzengolf"}], "ref": "golfforum.de", "toknum": 16615489382, "Left": [{"class": "strc", "str": "<p>"}, {"class": "", "str": "Jochen Kupitz: Vielleicht sollten wir dar\u00c31\u20444ber nachdenken, ob diese Ansichtsweise nicht zumindest im"}]}, {"Right": [{"class": "", "str": " auf 45 L\u00f6chern."}], "hitlen": "", "Tbl_refs": ["testfahrt.de"], "linegroup": "_", "Kwic": [{"class": "col0 coll", "str": " Spitzengolf"}], "ref": "testfahrt.de", "toknum": 17874385263, "Left": [{"class": "strc", "str": "<p>"}, {"class": "", "str": "Das 5-Sterne Hotel Sonnenalp liegt in traumhafter Alpenkulisse und bietet"}]}, {"Right": [{"class": "", "str": " in Australien und wurde dort am Ende nur noch von Scott getoppt."}], "hitlen": "", "Tbl_refs": ["golf.de"], "linegroup": "_", "Kwic": [{"class": "col0 coll", "str": " Spitzengolf"}], "ref": "golf.de", "toknum": 11192774980, "Left": [{"class": "", "str": "Der Brite zeigte nach dem Sieg beim WGC"}]}, {"Right": [{"class": "", "str": " allerdings, wenn Spieler minderer G\u00fcte gemeinsam mit Profis antreten."}], "hitlen": "", "Tbl_refs": ["bilanz.ch"], "linegroup": "_", "Kwic": [{"class": "col0 coll", "str": " Spitzengolf"}], "ref": "bilanz.ch", "toknum": 16777211538, "Left": [{"class": "", "str": "Besonders augenf\u00e4llig wird der Unterschied zwischen Alltags- und"}]}, {"Right": [{"class": "", "str": ", welches sich hier viele von ihm erwartet haben, konnte er bis jetzt noch nicht zeigen."}], "hitlen": "", "Tbl_refs": ["golfakademie-gmbh.de"], "linegroup": "_", "Kwic": [{"class": "col0 coll", "str": " Spitzengolf"}], "ref": "golfakademie-gmbh.de", "toknum": 17799842493, "Left": [{"class": "", "str": "Er zeigt zwar gutes Golf, aber das"}]}, {"Right": [{"class": "", "str": " zu bestehen."}], "hitlen": "", "Tbl_refs": ["golfsportmagazin.de"], "linegroup": "_", "Kwic": [{"class": "col0 coll", "str": " Spitzengolf"}], "ref": "golfsportmagazin.de", "toknum": 16074808557, "Left": [{"class": "", "str": "Neben Talent sind eine gute Schulung, ein passendes Umfeld, Trainingsflei\u00df und Wille Voraussetzung um im"}]}, {"Right": [{"class": "", "str": "."}], "hitlen": "", "Tbl_refs": ["golfforum.de"], "linegroup": "_", "Kwic": [{"class": "col0 coll", "str": " Spitzengolfs"}], "ref": "golfforum.de", "toknum": 9445195855, "Left": [{"class": "", "str": "Da beneide ich dich um die vielen Erlebnisse, die dir als Trainer bis jetzt erspart geblieben sind in der Realit\u00c3\u00a4t des deutschen"}]}, {"Right": [{"class": "", "str": " gepaart mit einer herrlichen Leichtigkeit und N\u00e4he genie\u00dfen."}, {"class": "strc", "str": "</p>"}], "hitlen": "", "Tbl_refs": ["golfsportmagazin.de"], "linegroup": "_", "Kwic": [{"class": "col0 coll", "str": " Spitzengolf"}], "ref": "golfsportmagazin.de", "toknum": 7042321658, "Left": [{"class": "", "str": "Die rund 10.000 Golffans, die trotz des schlechten Wetters gekommen waren, konnten"}]}, {"Right": [{"class": "", "str": " und weltbekannten Pferderennen."}], "hitlen": "", "Tbl_refs": ["shamrock-reisen.ch"], "linegroup": "_", "Kwic": [{"class": "col0 coll", "str": " Spitzengolf"}], "ref": "shamrock-reisen.ch", "toknum": 7663072426, "Left": [{"class": "", "str": "Sie ist begehrt wegen ihres nat\u00fcrlichen Charmes, den historischen St\u00e4tten Newgrange und Clonmacnoise, dem"}]}, {"Right": [{"class": "", "str": " darf man feste Gr\u00c3\u00b6\u00c3\u0178en wie die belegbaren Ergebnisse der Vergangenheit nicht au\u00c3\u0178er acht lassen."}], "hitlen": "", "Tbl_refs": ["golfforum.de"], "linegroup": "_", "Kwic": [{"class": "col0 coll", "str": " Spitzengolf"}], "ref": "golfforum.de", "toknum": 9445197490, "Left": [{"class": "", "str": "Auf der Suche nach dem erfolgreichen Weg zum"}]}, {"Right": [{"class": "", "str": " in Deutschland unterst\u00fctzen und aktiver Teil eines gro\u00dfartigen F\u00f6rdervereins sein will."}], "hitlen": "", "Tbl_refs": ["golfmagazin.de"], "linegroup": "_", "Kwic": [{"class": "col0 coll", "str": " Spitzengolf"}], "ref": "golfmagazin.de", "toknum": 15250947154, "Left": [{"class": "strc", "str": "<p>"}, {"class": "", "str": "Die Mitgliedschaft im \"Club2018\" ist f\u00fcr jeden m\u00f6glich, der leidenschaftlich"}]}, {"Right": [{"class": "", "str": " mitten in den Bergen."}, {"class": "strc", "str": "</p>"}], "hitlen": "", "Tbl_refs": ["econova.at"], "linegroup": "_", "Kwic": [{"class": "col0 coll", "str": "Spitzengolf"}], "ref": "econova.at", "toknum": 4487916352, "Left": [{"class": "strc", "str": "<p>"}]}, {"Right": [{"class": "", "str": " zu gewinnen sein w\u00fcrde."}, {"class": "strc", "str": "</p>"}], "hitlen": "", "Tbl_refs": ["golf.de"], "linegroup": "_", "Kwic": [{"class": "col0 coll", "str": " Spitzengolf"}], "ref": "golf.de", "toknum": 3614694216, "Left": [{"class": "", "str": "Ganz stark, wie der Hubbelrather den Ball stopfte und damit das Signal gab, dass dieses Match nur mit echtem"}]}, {"Right": [{"class": "", "str": "."}], "hitlen": "", "Tbl_refs": ["golf.at"], "linegroup": "_", "Kwic": [{"class": "col0 coll", "str": " Spitzengolfs"}], "ref": "golf.at", "toknum": 4405215133, "Left": [{"class": "strc", "str": "<p>"}, {"class": "", "str": "Auf der provisorischen Nennliste f\u00fcr das erste \u00f6sterreichische Top-Turnier der neuen Saison findet sich eine gro\u00dfe Anzahl von Playing Pros und Nachwuchshoffnungen des heimischen"}]}, {"Right": [{"class": "", "str": " und bezwang Longhitterin Kirchmayr, bei einem Score von sechs Schl\u00e4gen unter Par, am 18. Loch mit 1auf."}], "hitlen": "", "Tbl_refs": ["golf.de"], "linegroup": "_", "Kwic": [{"class": "col0 coll", "str": " Spitzengolf"}], "ref": "golf.de", "toknum": 3743966963, "Left": [{"class": "", "str": "Cnops zeigte"}]}, {"Right": [{"class": "", "str": " so stark da, wie noch nie mit drei Spielern auf der European Tour, der h\u00f6chsten Spielklasse Europas."}], "hitlen": "", "Tbl_refs": ["igcv.de"], "linegroup": "_", "Kwic": [{"class": "col0 coll", "str": " Spitzengolf"}], "ref": "igcv.de", "toknum": 1500210385, "Left": [{"class": "", "str": "Trotz der j\u00fcngsten Entt\u00e4uschungen steht \u00d6sterreich im"}]}, {"Right": [{"class": "", "str": ", oft mittelm\u00e4ssiges und manchmal sogar (leider) entt\u00e4uschendes Golf."}], "hitlen": "", "Tbl_refs": ["blogspot.de"], "linegroup": "_", "Kwic": [{"class": "col0 coll", "str": " Spitzengolf"}], "ref": "blogspot.de", "toknum": 2736018245, "Left": [{"class": "strc", "str": "<p>"}, {"class": "", "str": "Und ich sah bei den Damen, gemeinsam mit vielen anderen G\u00e4sten, manchmal echtes"}]}, {"Right": [{"class": "", "str": " ausgerichtet ist."}, {"class": "strc", "str": "</p>"}], "hitlen": "", "Tbl_refs": ["golfsuisse.ch"], "linegroup": "_", "Kwic": [{"class": "col0 coll", "str": " Spitzengolf"}], "ref": "golfsuisse.ch", "toknum": 15411585541, "Left": [{"class": "strc", "str": "<p>"}, {"class": "", "str": "F\u00f6rdern des talentierten Golfnachwuchs hin zum Leistungs- und Spitzensport, die zielgerichtet mit qualifizierten Trainern und Betreuern in den Regionen erfolgt und am internationalen"}]}, {"Right": [{"class": "", "str": " undgewann den Saisonauftakt, verlor aber einige Pl\u00e4tze in der Weltrangliste, weildie Champions Tour keine Weltranglistenpunkte vergibt."}], "hitlen": "", "Tbl_refs": ["golfakademie-gmbh.de"], "linegroup": "_", "Kwic": [{"class": "col0 coll", "str": " Spitzengolf"}], "ref": "golfakademie-gmbh.de", "toknum": 8635512119, "Left": [{"class": "", "str": "Bernhard Langer hingegen, zeigte"}]}, {"Right": [{"class": "", "str": " \u00c2\"live\u00c2\" zu erleben."}, {"class": "strc", "str": "</p>"}], "hitlen": "", "Tbl_refs": ["gb-go.de"], "linegroup": "_", "Kwic": [{"class": "col0 coll", "str": " Spitzengolf"}], "ref": "gb-go.de", "toknum": 1672782826, "Left": [{"class": "", "str": "Und selbstverst\u00c3\u00a4ndlich nutzten die G\u00c3\u00a4ste die Gelegenheit, entweder einmal selbst zum Schl\u00c3\u00a4ger zu greifen, oder aber"}]}, {"Right": [{"class": "", "str": " \"Made in Switzerland\" im Golf-Forum : Leider gibt es ja im Golf-Spitzensport noch nicht sehr viele Schweizer Erfolgsstories."}], "hitlen": "", "Tbl_refs": ["golf-forum.ch"], "linegroup": "_", "Kwic": [{"class": "col0 coll", "str": " Spitzengolf"}], "ref": "golf-forum.ch", "toknum": 5946244637, "Left": [{"class": "strc", "str": "<p>"}, {"class": "", "str": "Eine Diskussion zum Thema"}]}, {"Right": [{"class": "", "str": " einmal live erleben wollen, sollten sich das Wochenende vom 7. bis 9. Juni 2013 rot im Kalender anstreichen."}], "hitlen": "", "Tbl_refs": ["golfsportmagazin.de"], "linegroup": "_", "Kwic": [{"class": "col0 coll", "str": " Spitzengolf"}], "ref": "golfsportmagazin.de", "toknum": 7043336546, "Left": [{"class": "strc", "str": "<p>"}, {"class": "", "str": "Golffans, aber auch alle Sportinteressierten, die"}]}, {"Right": [{"class": "", "str": "."}], "hitlen": "", "Tbl_refs": ["golfclubhoesel.de"], "linegroup": "_", "Kwic": [{"class": "col0 coll", "str": " Spitzengolf"}], "ref": "golfclubhoesel.de", "toknum": 15497302292, "Left": [{"class": "strc", "str": "<p>"}, {"class": "", "str": "Ali Durmus, Mitglied der Platzmannschaft und Single-Handicapper, spielte an diesem Tag mit 19 Bruttopunkten und einem Birdie auf der \"neuen\" 18 ein"}]}, {"Right": [{"class": "", "str": " direkt vor der Haust\u00fcr zu erleben."}], "hitlen": "", "Tbl_refs": ["hcp54.de"], "linegroup": "_", "Kwic": [{"class": "col0 coll", "str": " Spitzengolf"}], "ref": "hcp54.de", "toknum": 11529926983, "Left": [{"class": "", "str": "Somit war dieses (Show-)Turnier eine hervorragende M\u00f6glichkeit f\u00fcr (Nord-)Deutsche internationales"}]}, {"Right": [{"class": "", "str": " von den US Open, den British Open und der PGA Championship \u00fcbertragen."}], "hitlen": "", "Tbl_refs": ["golftime.de"], "linegroup": "_", "Kwic": [{"class": "col0 coll", "str": " Spitzengolf"}], "ref": "golftime.de", "toknum": 14046675027, "Left": [{"class": "strc", "str": "<p>"}, {"class": "", "str": "M\u00fcnchen - Auch in den kommenden drei Jahren wird Sky live und exklusiv"}]}, {"Right": [{"class": "", "str": " eigeneten, unterst\u00fctzte er Bernhard Langer - ein in seinen Augen \u00fcberaus hoffnungsvolles Spielertalent."}], "hitlen": "", "Tbl_refs": ["golf-news.de"], "linegroup": "_", "Kwic": [{"class": "col0 coll", "str": " Spitzengolf"}], "ref": "golf-news.de", "toknum": 1058872341, "Left": [{"class": "", "str": "Entgegen der damals vorherrschenden Meinung, nach der sich die Deutschen offenkundig nicht f\u00fcr den"}]}, {"Right": [{"class": "", "str": " der Extraklasse: Dirk U. Hindrichs und die Sch\u00fcco Markenbotschafter."}], "hitlen": "", "Tbl_refs": ["unigolftour.de"], "linegroup": "_", "Kwic": [{"class": "col0 coll", "str": " Spitzengolf"}], "ref": "unigolftour.de", "toknum": 9721152152, "Left": [{"class": "strc", "str": "<p>"}, {"class": "", "str": "Eine klassische Zeitung w\u00fcrde sich jetzt folgende Bildunterschrift ausdenken: \"Freuen sich jetzt schon auf"}]}, {"Right": [{"class": "", "str": " eine Herzensangelegenheit ist und der mithelfen will, die Vision der Teilnahme deutscher Talente beim Kampf der Kontinente zu verwirklichen."}], "hitlen": "", "Tbl_refs": ["gc-slr.de"], "linegroup": "_", "Kwic": [{"class": "col0 coll", "str": " Spitzengolfs"}], "ref": "gc-slr.de", "toknum": 12390666486, "Left": [{"class": "", "str": "Mitmachen kann jeder, dem die Unterst\u00c31\u20444tzung des"}]}, {"Right": [{"class": "", "str": " mit Panoramablick auf 3 Pl\u00e4tzen mit 18+18+9 Loch."}, {"class": "strc", "str": "</p>"}], "hitlen": "", "Tbl_refs": ["orangetravel.de"], "linegroup": "_", "Kwic": [{"class": "col0 coll", "str": " Spitzengolf"}], "ref": "orangetravel.de", "toknum": 17861182308, "Left": [{"class": "strc", "str": "<p>"}, {"class": "", "str": "Vom Hotel Exquisit erreichen Sie nach nur wenigen Kilometern das im Mai 2004 neu er\u00f6ffnete Golfresort Oberallg\u00e4u"}]}, {"Right": [{"class": "", "str": " ausgerichtet ist."}, {"class": "strc", "str": "</p>"}], "hitlen": "", "Tbl_refs": ["golfsuisse.ch"], "linegroup": "_", "Kwic": [{"class": "col0 coll", "str": " Spitzengolf"}], "ref": "golfsuisse.ch", "toknum": 15411585281, "Left": [{"class": "strc", "str": "<p>"}, {"class": "", "str": "Die ASG f\u00f6rdert den talentierten Golfnachwuchs hin zum Leistungs- und Spitzensport, dies zielgerichtet mit qualifizierten Trainern und Betreuern auf nationaler Ebene, wobei die F\u00f6rderung am internationalen"}]}, {"Right": [{"class": "", "str": " f\u00fchrte."}], "hitlen": "", "Tbl_refs": ["igcv.de"], "linegroup": "_", "Kwic": [{"class": "col0 coll", "str": " Spitzengolf"}], "ref": "igcv.de", "toknum": 1301902394, "Left": [{"class": "strc", "str": "<p>"}, {"class": "", "str": "Alles Faktoren, die beim Shooting-Star Kaymer zutreffen: Da ist einmal das famili\u00e4re Umfeld mit Vater Horst, Hcp 4, der seine beiden S\u00f6hne gezielt zum"}]}, {"Right": [{"class": "", "str": " wird."}], "hitlen": "", "Tbl_refs": ["buch.de"], "linegroup": "_", "Kwic": [{"class": "col0 coll", "str": " Spitzengolf"}], "ref": "buch.de", "toknum": 3596676508, "Left": [{"class": "", "str": "Albert Hirsch, Vorstandssprecher von buch.de: \"Nach dem erfolgreichen Turnier im letzten Jahr sind wir sicher, dass auch die dritte Austragung zu einem spannenden und hochkar\u00e4tigen Gro\u00dfereignis im internationalen"}]}, {"Right": [{"class": "", "str": ", eine Vielzahl von Top-Spielern und vor allem den Besten der Besten geboten hatte: Tiger Woods."}, {"class": "strc", "str": "</p>"}], "hitlen": "", "Tbl_refs": ["gc-slr.de"], "linegroup": "_", "Kwic": [{"class": "col0 coll", "str": " Spitzengolf"}], "ref": "gc-slr.de", "toknum": 11024313335, "Left": [{"class": "", "str": "Damit endete ein kurzes, aber bedeutendes Kapitel Clubgeschichte, das Mitgliedern und Besuchern absolutes"}]}, {"Right": [{"class": "", "str": " zu sehen - mit vier Extral\u00f6chern und einem gro\u00dfartigen Sieger in Matteo Manassero."}], "hitlen": "", "Tbl_refs": ["golf.de"], "linegroup": "_", "Kwic": [{"class": "col0 coll", "str": " Spitzengolf"}], "ref": "golf.de", "toknum": 3927479562, "Left": [{"class": "", "str": "Bei traumhaften Bedingungen bekamen mehr als 25.000 Zuschauer auf dem West Course des Wentworth Clubs vor den Toren von London"}]}, {"Right": [{"class": "", "str": ", eine exzellente Organisation und eine besonders angenehme, famili\u00e4re Atmosph\u00e4re. 2013 kehrt Deutschlands einziges European Tour Turnier zum 25. Jubil\u00e4um zur\u00fcck nach M\u00fcnchen."}], "hitlen": "", "Tbl_refs": ["bmw.de"], "linegroup": "_", "Kwic": [{"class": "col0 coll", "str": " Spitzengolf"}], "ref": "bmw.de", "toknum": 170352112, "Left": [{"class": "strc", "str": "<p>"}, {"class": "", "str": "Seit fast einem Vierteljahrhundert steht die BMW International Open f\u00fcr internationales"}]}, {"Right": [{"class": "", "str": " zu erkennen - F\u00f6rderstrukturen zu schaffen, welche die strikte Trennung zwischen Professionals und Amateuren, f\u00fcr das Ziel Olympia bzw. die Vision Gold, ein St\u00fcck weit vereint."}], "hitlen": "", "Tbl_refs": ["gvnb.de"], "linegroup": "_", "Kwic": [{"class": "col0 coll", "str": " Spitzengolf"}], "ref": "gvnb.de", "toknum": 12649686695, "Left": [{"class": "", "str": "Folglich ist hier die Kernaufgabe f\u00fcr das deutsche"}]}, {"Right": [{"class": "", "str": " gefunden."}, {"class": "strc", "str": "</p>"}], "hitlen": "", "Tbl_refs": ["golfsportmagazin.de"], "linegroup": "_", "Kwic": [{"class": "col0 coll", "str": " Spitzengolf"}], "ref": "golfsportmagazin.de", "toknum": 17774826658, "Left": [{"class": "strc", "str": "<p>"}, {"class": "", "str": "Bereits mehrmals habe ich geschrieben, wenn 10 -15 deutsche Spieler auf den verschiedenen Touren zu finden w\u00e4ren, wie Schweden, Italiener, von Engl\u00e4ndern, Amerikanern, S\u00fcdafrikaner abgesehen, ist der Anschluss an"}]}, {"Right": [{"class": "", "str": " Ende Juni bzw. Anfang Juli: \"Neben zahlreichen Top-Golfern wird Legende Gary Player anwesend sein."}], "hitlen": "", "Tbl_refs": ["pga.de"], "linegroup": "_", "Kwic": [{"class": "col0 coll", "str": " Spitzengolf"}], "ref": "pga.de", "toknum": 13605165231, "Left": [{"class": "", "str": "Und Karsten Wehmeier, Leiter Kommunikation des Geldinstituts mit Sitz in Hamburg, macht schon mal Appetit auf drei Tage"}]}, {"Right": [{"class": "", "str": " zu erreichen, mehr als zufrieden sein."}, {"class": "strc", "str": "</p>"}], "hitlen": "", "Tbl_refs": ["gb-go.de"], "linegroup": "_", "Kwic": [{"class": "col0 coll", "str": " Spitzengolf"}], "ref": "gb-go.de", "toknum": 13042294032, "Left": [{"class": "strc", "str": "<p>"}, {"class": "", "str": "Aber auch der Titelsponsor, die Wild Werke in Eppelheim bei Heidelberg, die sich die F\u00c3\u00b6rderung junger Spitzengolfer auf die Fahnen geschrieben haben, kann mit seiner Erwartung absolutes"}]}, {"Right": [{"class": "", "str": " und ab diesem Jahr werden sich davon auch die Golffans im Rheinland aus unmittelbarer N\u00e4he \u00fcberzeugen k\u00f6nnen."}], "hitlen": "", "Tbl_refs": ["das-tv-programm.de"], "linegroup": "_", "Kwic": [{"class": "col0 coll", "str": " Spitzengolf"}], "ref": "das-tv-programm.de", "toknum": 4645387861, "Left": [{"class": "", "str": "F\u00fcr die deutschen Zuschauer wird vor allem die BMW International Open 2012 von Interesse sein: bereits seit 22 Jahren steht der Event f\u00fcr internationales"}]}, {"Right": [{"class": "", "str": " der jungen Amateure erlebten, sondern auch selbst aktiv an den Sport herangef\u00c31\u20444hrt wurden."}], "hitlen": "", "Tbl_refs": ["gc-slr.de"], "linegroup": "_", "Kwic": [{"class": "col0 coll", "str": " Spitzengolf"}], "ref": "gc-slr.de", "toknum": 3818157509, "Left": [{"class": "", "str": "Freilich war der Club nicht nur im Netz aktiv: So gab es eigens konzipierte Golfprogramme f\u00c31\u20444r Schulklassen, die das Turnier im Rahmen ihres Wandertags besuchten und nicht nur das"}]}, {"Right": [{"class": "", "str": " zu eignen.\u00e2 Die Golfnation wagte offensichtlich noch immer nicht zu hoffen."}, {"class": "strc", "str": "</p>"}], "hitlen": "", "Tbl_refs": ["golf.de"], "linegroup": "_", "Kwic": [{"class": "col0 coll", "str": " Spitzengolf"}], "ref": "golf.de", "toknum": 12398959937, "Left": [{"class": "", "str": "Noch drei Jahre sp\u00c3\u00a4ter blieb ausgerechnet der ehemalige Champion Erik Sellschopp, damals 61 Jahre alt, skeptisch und verstieg sich in absurde Theorien: \u00e2Unsere absolute Spitze hat sich etwas verbessert, aber wir Deutschen scheinen uns nicht zum"}]}, {"Right": [{"class": "", "str": " und Spitzengolfer nur nach Leadbetters Schwungverst\u00c3\u00a4ndis hervorbringen kann, w\u00c3\u00a4hrend mit Olivers Schwungverst\u00c3\u00a4ndnis Hobbygolfern das Leben erleichtert wird, aber Leistungsgolf demzufolge nicht erzielt werden kann?"}, {"class": "strc", "str": "</p>"}], "hitlen": "", "Tbl_refs": ["golfforum.de"], "linegroup": "_", "Kwic": [{"class": "col0 coll", "str": " Spitzengolf"}], "ref": "golfforum.de", "toknum": 18252245080, "Left": [{"class": "strc", "str": "<p>"}, {"class": "", "str": "Im Umkehrschlu\u00c3\u0178 und auf die Spitze getrieben, w\u00c31\u20444rde das doch dann aber bedeuten, dass man"}]}, {"Right": [{"class": "", "str": ", siehe Teilnehmer auf der European Tour oder der Challange -Tour seit Jahren mehr Spieler stellt als Deutschland."}], "hitlen": "", "Tbl_refs": ["golfsportmagazin.de"], "linegroup": "_", "Kwic": [{"class": "col0 coll", "str": " Spitzengolfs"}], "ref": "golfsportmagazin.de", "toknum": 16074808500, "Left": [{"class": "", "str": "Trotzdem sei die Frage erlaubt, warum L\u00e4nder wie Spanien, Italien, Schweden und in letzter Zeit sogar \u00d6sterreich in der Breite des"}]}, {"Right": [{"class": "", "str": " der europ\u00e4ischen Damen-Golfelite erleben."}], "hitlen": "", "Tbl_refs": ["pegini.de"], "linegroup": "_", "Kwic": [{"class": "col0 coll", "str": " Spitzengolf"}], "ref": "pegini.de", "toknum": 6999527982, "Left": [{"class": "", "str": "Dort werden die Kinder zusammen mit ihren Betreuern"}]}, {"Right": [{"class": "", "str": " an diesem au\u00dfergew\u00f6hnlichen und traditionsreichen Ort erzeugt bei jedem eingefleischten Golfer eine..."}], "hitlen": "", "Tbl_refs": ["einfach-meer.de"], "linegroup": "_", "Kwic": [{"class": "col0 coll", "str": " Spitzengolf"}], "ref": "einfach-meer.de", "toknum": 7190730999, "Left": [{"class": "", "str": "Die Vorstellung an vier Tage"}]}, {"Right": [{"class": "", "str": ", den Breitensport und die Golfschl\u00e4gerindustrie."}, {"class": "strc", "str": "</p>"}], "hitlen": "", "Tbl_refs": ["golfit.at"], "linegroup": "_", "Kwic": [{"class": "col0 coll", "str": " Spitzengolf"}], "ref": "golfit.at", "toknum": 9385400445, "Left": [{"class": "", "str": "Das er\u00f6ffnet auch neue Chancen f\u00fcr das \u00f6sterreichische"}]}, {"Right": [{"class": "", "str": " l\u00e4sst keine Fehler zu, das ist in meisten anderen Sportarten anders, da k\u00f6nnen Fehler wieder korrigiert werden."}], "hitlen": "", "Tbl_refs": ["vol.at"], "linegroup": "_", "Kwic": [{"class": "col0 coll", "str": "Spitzengolf"}], "ref": "vol.at", "toknum": 19523619309, "Left": [{"class": "", "str": "\""}]}, {"Right": [{"class": "", "str": " im DSF: Die Highlights der 21. BMW International Open"}, {"class": "strc", "str": "</p>"}], "hitlen": "", "Tbl_refs": ["golf-news.de"], "linegroup": "_", "Kwic": [{"class": "col0 coll", "str": "Spitzengolf"}], "ref": "golf-news.de", "toknum": 14233717822, "Left": [{"class": "strc", "str": "<p>"}]}, {"Right": [{"class": "", "str": ", aber die verpatzte erste Rundekostete sie die Tourkarte."}], "hitlen": "", "Tbl_refs": ["golfakademie-gmbh.de"], "linegroup": "_", "Kwic": [{"class": "col0 coll", "str": " Spitzengolf"}], "ref": "golfakademie-gmbh.de", "toknum": 11116281069, "Left": [{"class": "", "str": "Ab derZweiten Runde spielte sie wieder"}]}, {"Right": [{"class": "", "str": "\", so Volker Schwartz, Gesch\u00e4ftsf\u00fchrer des Hartl Resorts."}], "hitlen": "", "Tbl_refs": ["e-pro-motion.de"], "linegroup": "_", "Kwic": [{"class": "col0 coll", "str": " Spitzengolf"}], "ref": "e-pro-motion.de", "toknum": 3023332962, "Left": [{"class": "strc", "str": "<p>"}, {"class": "", "str": "\"In Deutschland tut sich wieder was im"}]}, {"Right": [{"class": "", "str": " \"Made in Switzerland\""}, {"class": "strc", "str": "</p>"}], "hitlen": "", "Tbl_refs": ["golf-forum.ch"], "linegroup": "_", "Kwic": [{"class": "col0 coll", "str": "Spitzengolf"}], "ref": "golf-forum.ch", "toknum": 5946244669, "Left": [{"class": "strc", "str": "<p>"}]}, {"Right": [{"class": "strc", "str": "</p>"}], "hitlen": "", "Tbl_refs": ["gc-coburg.de"], "linegroup": "_", "Kwic": [{"class": "col0 coll", "str": " Spitzengolf"}], "ref": "gc-coburg.de", "toknum": 17825716853, "Left": [{"class": "strc", "str": "<p>"}, {"class": "", "str": "Bettina Knorr und Christian H\u00f6llein zeigten"}]}, {"Right": [{"class": "", "str": ": Professional: 22 Jahre Durchschnitt 70 Schl\u00c3\u00a4ge auf Tour Pl\u00c3\u00a4tzen"}, {"class": "strc", "str": "</p>"}], "hitlen": "", "Tbl_refs": ["golfforum.de"], "linegroup": "_", "Kwic": [{"class": "col0 coll", "str": " Spitzengolf"}], "ref": "golfforum.de", "toknum": 19294399921, "Left": [{"class": "strc", "str": "<p>"}, {"class": "", "str": "Im Vierer Jahres Rhythmus zum"}]}, {"Right": [{"class": "", "str": " von einst jedenfalls ist in weite ferne ger\u00c31\u20444ckt."}], "hitlen": "", "Tbl_refs": ["3d-zeitschrift.de"], "linegroup": "_", "Kwic": [{"class": "col0 coll", "str": " Spitzengolf"}], "ref": "3d-zeitschrift.de", "toknum": 17370521495, "Left": [{"class": "strc", "str": "<p>"}, {"class": "", "str": "40 green titel nykredit masters eigentlich den h\u00c3\u00b6hepunkt ihrer laufbahn golfsports unter neuen gesichtspunkten zu betrachten. das"}]}, {"Right": [{"class": "", "str": " in D\u00fcsseldorf-Grafenberg sehen werden\", ist sich Gerd W. Kichniawy vom Turnier-Management sicher."}], "hitlen": "", "Tbl_refs": ["sportstadt-duesseldorf.de"], "linegroup": "_", "Kwic": [{"class": "col0 coll", "str": " Spitzengolf"}], "ref": "sportstadt-duesseldorf.de", "toknum": 15187631580, "Left": [{"class": "strc", "str": "<p>"}, {"class": "", "str": "\"Angesichts dieses tollen Teilnehmerfeldes sind wir sicher, dass wir absolutes"}]}, {"Right": [{"class": "", "str": " zu schaffen, einen weiteren wichtigen Schritt n\u00e4her."}], "hitlen": "", "Tbl_refs": ["golfsportmagazin.de"], "linegroup": "_", "Kwic": [{"class": "col0 coll", "str": " Spitzengolfs"}], "ref": "golfsportmagazin.de", "toknum": 11544274965, "Left": [{"class": "", "str": "\"Damit kommen wir unserem Ziel, die bestm\u00f6glichen Rahmenbedingungen f\u00fcr die F\u00f6rderung junger Talente und der Weiterentwicklung des deutschen"}]}, {"Right": [{"class": "", "str": " - vor kleiner Kulisse"}, {"class": "strc", "str": "</p>"}], "hitlen": "", "Tbl_refs": ["golf.de"], "linegroup": "_", "Kwic": [{"class": "col0 coll", "str": "Spitzengolf"}], "ref": "golf.de", "toknum": 12902530590, "Left": [{"class": "strc", "str": "<p>"}]}, {"Right": [{"class": "", "str": " bei uns."}, {"class": "strc", "str": "</p>"}], "hitlen": "", "Tbl_refs": ["golfsportmagazin.de"], "linegroup": "_", "Kwic": [{"class": "col0 coll", "str": " Spitzengolf"}], "ref": "golfsportmagazin.de", "toknum": 17774826619, "Left": [{"class": "strc", "str": "<p>"}, {"class": "", "str": "Anstelle sich in den klassischen Golfl\u00e4ndern umzusehen, von deren Verbandsstrukturen und Golfkultur zu lernen, kochen bei uns die Verb\u00e4nde eigene S\u00fcppchen \u2013 Darum \u00e4ndert sich seit Jahrzehnten nichts im"}]}, {"Right": [{"class": "", "str": " in Deutschland w\u00c3\u00a4ren mein Nationalstolz."}], "hitlen": "", "Tbl_refs": ["golfforum.de"], "linegroup": "_", "Kwic": [{"class": "col0 coll", "str": " Spitzengolf"}], "ref": "golfforum.de", "toknum": 9445198543, "Left": [{"class": "", "str": "In meinem Beitrag im Golfforum \u00e2\u20ac\u017eKritik am RTP\u00e2\u20ac\u0153 habe ich Sie glauben lassen, meine Beweggr\u00c31\u20444nde f\u00c31\u20444r erfolgreiches"}]}, {"Right": [{"class": "", "str": " im Gleichklang"}, {"class": "strc", "str": "</p>"}], "hitlen": "", "Tbl_refs": ["golfjournal.de"], "linegroup": "_", "Kwic": [{"class": "col0 coll", "str": " Spitzengolf"}], "ref": "golfjournal.de", "toknum": 17085001311, "Left": [{"class": "strc", "str": "<p>"}, {"class": "", "str": "Playoff:"}]}, {"Right": [{"class": "", "str": " aus Abenberg"}, {"class": "strc", "str": "</p>"}], "hitlen": "", "Tbl_refs": ["golfclubabenberg.de"], "linegroup": "_", "Kwic": [{"class": "col0 coll", "str": "Spitzengolf"}], "ref": "golfclubabenberg.de", "toknum": 1905241812, "Left": [{"class": "strc", "str": "<p>"}]}, {"Right": [{"class": "", "str": " als auch als die Lieblingswedges von Spielern, die das Spiel ernst nehmen und sich kontinuierlich verbessern wollen."}], "hitlen": "", "Tbl_refs": ["golfnrw-online.de"], "linegroup": "_", "Kwic": [{"class": "col0 coll", "str": " Spitzengolf"}], "ref": "golfnrw-online.de", "toknum": 1348088542, "Left": [{"class": "", "str": "Seit 1998 haben Vokey Design Wedges unglaubliche Erfolge erzielt, sowohl als die bevorzugte Wedges auf den Profitouren und im"}]}, {"Right": [{"class": "", "str": " der US PGA Tour und Eishockey aus der D..."}, {"class": "strc", "str": "</p>"}], "hitlen": "", "Tbl_refs": ["hansestadt-info.de"], "linegroup": "_", "Kwic": [{"class": "col0 coll", "str": " Spitzengolf"}], "ref": "hansestadt-info.de", "toknum": 8090193760, "Left": [{"class": "strc", "str": "<p>"}, {"class": "", "str": "Unterf\u00f6hring (ots) - 2. M\u00e4rz 2012. Neben den Begegnungen des 24. Spieltags der Bundesliga \u00fcbertr\u00e4gt Sky am Wochenende das R\u00f6mer Derby, drei Spiele aus der Premier League,"}]}, {"Right": [{"class": "", "str": " vornehmlich vortrifft: Der Schl\u00c3\u00a4gerschaft wird bei Leadbetters Ansatz im zweiten Teil der Ausholbewegung (ab 9 Uhr) steiler geschwungen und soll im Abschwung wieder auf die urspr\u00c31\u20444ngliche Ebene abgeflacht werden."}], "hitlen": "", "Tbl_refs": ["golfforum.de"], "linegroup": "_", "Kwic": [{"class": "col0 coll", "str": " Spitzengolf"}], "ref": "golfforum.de", "toknum": 10171607737, "Left": [{"class": "", "str": "Daher kam es bei ihm h\u00c3\u00a4ufig vor, dass aus einem harmlosen Slice heftige Sockets entstanden . Zudem favorisiert er ein (sehr effektives) Ebenmodell, welches man in der Welt de"}]}, {"Right": [{"class": "", "str": ", und wir meinen in diesem Fall Profi Golf, f\u00c3\u00b6rdert das Interesse der \u00c3\u2013ffentlichkeit."}], "hitlen": "", "Tbl_refs": ["golfforum.de"], "linegroup": "_", "Kwic": [{"class": "col0 coll", "str": "Spitzengolf"}], "ref": "golfforum.de", "toknum": 9440890896, "Left": []}, {"Right": [{"class": "", "str": " \"Made in Switzerland\""}, {"class": "strc", "str": "</p>"}], "hitlen": "", "Tbl_refs": ["golf-forum.ch"], "linegroup": "_", "Kwic": [{"class": "col0 coll", "str": "Spitzengolf"}], "ref": "golf-forum.ch", "toknum": 5946244627, "Left": [{"class": "strc", "str": "<p>"}]}], "request": {"username": "spahic", "gdex_enabled": "1", "pagesize": "200", "format": "json", "lpos": "-n", "q": "q[lemma=\"Spitzengolf\"]", "viewmode": "sentence", "async": "0", "corpname": "detenten13_rft3", "api_key": "159b841f61a64092bc630d20b0f56c93"}, "q": ["q[lemma=\"Spitzengolf\"]", "e100 "], "righttoleft": false, "finished": 1, "relsize": 0.0, "gdex_scores": {"15411585541": 0.6109482758620689, "9440890896": 0.7578571428571429, "5946244627": 0.17708333333333331, "11544274965": 0.10874999999999999, "5946244637": 0.6036538461538461, "12902530590": 0.085, "12902624946": 0.7235869565217391, "6999527982": 0.2999999999999999, "19566866611": 0.8409090909090909, "1301902394": 0.5391935483870968, "5946244669": 0.17708333333333331, "14233717822": 0.22500000000000006, "633379404": 0.84375, "9445195855": 0.6877777777777777, "15250947154": 0.6776923076923076, "14046675027": 0.5835714285714285, "4645387861": 0.5, "18252245080": 0.5, "3804931163": 0.765909090909091, "17085001311": 0.04, "3023332962": 0.19125, "9742003820": 0.7720454545454544, "17825716853": 0.1607142857142857, "17774826619": 0.05117647058823529, "9385400445": 0.284375, "1058872341": 0.5783870967741934, "16777211538": 0.7035714285714286, "965810325": 0.7907894736842104, "9721152152": 0.5771428571428571, "17774826658": 0.5011217948717949, "12649686695": 0.5022435897435897, "7663072426": 0.680952380952381, "13605165231": 0.5, "8010373296": 0.7340000000000001, "9445197490": 0.6776923076923076, "8138931": 0.85, "16074808500": 0.5, "10171607737": 0.0, "12324102842": 0.7442857142857144, "17799842493": 0.7034259259259258, "9445198543": 0.04142857142857143, "1500210385": 0.6301785714285714, "1905241812": 0.0, "9438465237": 0.7684210526315789, "1348088542": 0.0, "14211627232": 0.8, "11116281069": 0.21176470588235294, "3743966963": 0.6330434782608695, "12390666486": 0.575, "7190730999": 0.29078947368421043, "7042321658": 0.6833333333333332, "15411585281": 0.5461363636363636, "3927479562": 0.5155357142857143, "13042294032": 0.5, "15497302292": 0.5942857142857142, "14229572901": 0.8375, "8635512119": 0.6102500000000001, "4487916352": 0.6770833333333333, "12398959937": 0.5, "11534573963": 0.76, "11192774980": 0.71375, "2736018245": 0.6205357142857142, "11529926983": 0.5841346153846153, "3614694216": 0.6588888888888889, "10578186073": 0.7722222222222223, "8090193760": 0.0, "7043336546": 0.5948275862068965, "17861182308": 0.5685887096774193, "16615489382": 0.7209090909090909, "17874385263": 0.72, "11544274815": 0.7684210526315789, "11794566027": 0.76, "16074808557": 0.6933928571428573, "17370521495": 0.1275, "3596676508": 0.5332142857142856, "4405215133": 0.6346153846153846, "3628102049": 0.7676470588235295, "3456457641": 0.7368421052631579, "19294399921": 0.14250000000000004, "965809586": 0.7863636363636364, "9445195763": 0.78, "3818157509": 0.5, "13815711479": 0.8181818181818182, "13842782669": 0.8068181818181819, "13171952594": 0.7597222222222223, "15673400276": 0.8777777777777778, "9351953370": 0.7264705882352942, "15187631580": 0.1108928571428571, "1672782826": 0.605, "19523619309": 0.2792045454545453, "170352112": 0.5023684210526316, "12904187475": 0.7925, "11024313335": 0.5205147058823529, "965810168": 0.825}, "Desc": [{"nicearg": "Spitzengolf", "tourl": "q=q%5Blemma%3D%22Spitzengolf%22%5D", "rel": 0.0, "arg": "[lemma=\"Spitzengolf\"]", "op": "Query", "size": 94}, {"nicearg": "", "tourl": "q=q%5Blemma%3D%22Spitzengolf%22%5D&q=e100+", "rel": 0.0, "arg": "100 ", "op": "GDEX", "size": 94}], "concsize": 94, "port": 0, "api_version": "3.112.9", "fullsize": 94}