{"Sort_idx": [], "sc_strcts": [["doc", "doc"], ["s", "s"]], "Lines": [{"Right": [{"class": "", "str": " von Jerusalem und Titularherzog von Schwaben ."}], "hitlen": "", "Tbl_refs": ["#617884949"], "linegroup": "_", "Kwic": [{"class": "col0 coll", "str": " Titulark\u00f6nig"}], "ref": "#617884949", "toknum": 617884949, "Left": [{"class": "", "str": "Die Hohenstaufen-Partei w\u00e4hlte ihn deshalb zum"}]}, {"Right": [{"class": "", "str": " von Huai-nan , verhielt sich gegen\u00fcber dem Kaiserhaus nicht gerade botm\u00e4\u00dfig ."}], "hitlen": "", "Tbl_refs": ["#746403110"], "linegroup": "_", "Kwic": [{"class": "col0 coll", "str": " Titulark\u00f6nig"}], "ref": "#746403110", "toknum": 746403110, "Left": [{"class": "", "str": "An ( um 178-um 122 ) ,"}]}, {"Right": [{"class": "", "str": " von Jerusalem , Sizilien und Aragon auch die Anspr\u00fcche auf den lateinischen Kaisertitel geerbt hatte ."}], "hitlen": "", "Tbl_refs": ["#216193882"], "linegroup": "_", "Kwic": [{"class": "col0 coll", "str": " Titulark\u00f6nig"}], "ref": "#216193882", "toknum": 216193882, "Left": [{"class": "", "str": "Dieses j\u00fcngere Haus Anjou , das im 14. und 15. Jahrhundert mit wechselndem Erfolg auch Anspruch auf die K\u00f6nigskrone von Sizilien ( genauer : auf das Teilreich von Neapel ) erhob , starb 1480 mit Graf Rene von der Provence aus , der als"}]}, {"Right": [{"class": "", "str": " von Neapel und Sizilien , verheiratet , die Anspr\u00fcche beider H\u00e4user auf Neapel und Sizilien sollten vereint werden ."}], "hitlen": "", "Tbl_refs": ["#575008935"], "linegroup": "_", "Kwic": [{"class": "col0 coll", "str": " Titulark\u00f6nig"}], "ref": "#575008935", "toknum": 575008935, "Left": [{"class": "", "str": "Aufgrund politischer Erw\u00e4gungen wird sie 1400 mit Ludwig II von Anjou ,"}]}, {"Right": [{"class": "", "str": " Lhazang Khan , den Mandschukaiser in China um Hilfe ."}], "hitlen": "", "Tbl_refs": ["#381312294"], "linegroup": "_", "Kwic": [{"class": "col0 coll", "str": " Titulark\u00f6nig"}], "ref": "#381312294", "toknum": 381312294, "Left": [{"class": "", "str": "So rief der tibetische"}]}, {"Right": [{"class": "", "str": " von Huai-nan , zur\u00fcckgef\u00fchrt wird , tr\u00e4gt den Titel Shuo-shan , \" Gebirge von Argumenten \" , und ist ganz \u00e4hnlich angelegt wie das entsprechende Kapitel Shuo-y\u00fcan 16 ."}], "hitlen": "", "Tbl_refs": ["#746403073"], "linegroup": "_", "Kwic": [{"class": "col0 coll", "str": " Titulark\u00f6nig"}], "ref": "#746403073", "toknum": 746403073, "Left": [{"class": "", "str": "An ( um 178 - um 122 ) , den"}]}, {"Right": [{"class": "", "str": " von Ch'en , unsterblich gepriesen hatte ."}], "hitlen": "", "Tbl_refs": ["#746496438"], "linegroup": "_", "Kwic": [{"class": "col0 coll", "str": " Titulark\u00f6nig"}], "ref": "#746496438", "toknum": 746496438, "Left": [{"class": "", "str": "F\u00fcr die Narzisse fanden sie einen besonderen Vergleich - mit der zauberhaften \" Fee vom Flusse Lo \" , die Ts'ao Chih ( 192-232 ) ,"}]}], "request": {"username": "spahic", "gdex_enabled": "1", "pagesize": "200", "format": "json", "lpos": "-n", "q": "q[lemma=\"Titulark\u00f6nig\"]", "viewmode": "sentence", "async": "0", "corpname": "sdewac2", "api_key": "159b841f61a64092bc630d20b0f56c93"}, "q": ["q[lemma=\"Titulark\u00f6nig\"]", "e100 "], "righttoleft": false, "finished": 1, "relsize": 0.0, "gdex_scores": {"746403073": 0.5, "746403110": 0.53125, "381312294": 0.578375, "575008935": 0.5, "617884949": 0.6063988095238095, "746496438": 0.5, "216193882": 0.5}, "Desc": [{"nicearg": "Titulark\u00f6nig", "tourl": "q=q%5Blemma%3D%22Titulark%C3%B6nig%22%5D", "rel": 0.01, "arg": "[lemma=\"Titulark\u00f6nig\"]", "op": "Query", "size": 7}, {"nicearg": "", "tourl": "q=q%5Blemma%3D%22Titulark%C3%B6nig%22%5D&q=e100+", "rel": 0.01, "arg": "100 ", "op": "GDEX", "size": 7}], "concsize": 7, "port": 0, "api_version": "3.112.9", "fullsize": 7}